[
  [
    {
      "Candidate": "",
      "Ken Washington": "Ken Washington",
      "Jacque Whaumbush": "Jacque Whaumbush",
      "Kathryn S Huggins": "Kathryn S Huggins",
      "Lisa Rhodes": "Lisa Rhodes",
      "Monica Maria Djerassi": "Monica Maria Djerassi",
      "Willie Jordan": "Willie Jordan",
      "Write In": "Write In",
      "ward": 27,
      "division": "All"
    },
    {
      "Candidate": "Ken Washington",
      "Ken Washington": "12",
      "Jacque Whaumbush": "33",
      "Kathryn S Huggins": "32",
      "Lisa Rhodes": "33",
      "Monica Maria Djerassi": "34",
      "Willie Jordan": "30",
      "Write In": "1",
      "ward": 27,
      "division": "All"
    },
    {
      "Candidate": "Jacque Whaumbush",
      "Ken Washington": "33",
      "Jacque Whaumbush": "6",
      "Kathryn S Huggins": "31",
      "Lisa Rhodes": "31",
      "Monica Maria Djerassi": "31",
      "Willie Jordan": "28",
      "Write In": "0",
      "ward": 27,
      "division": "All"
    },
    {
      "Candidate": "Kathryn S Huggins",
      "Ken Washington": "32",
      "Jacque Whaumbush": "31",
      "Kathryn S Huggins": "4",
      "Lisa Rhodes": "36",
      "Monica Maria Djerassi": "35",
      "Willie Jordan": "29",
      "Write In": "0",
      "ward": 27,
      "division": "All"
    },
    {
      "Candidate": "Lisa Rhodes",
      "Ken Washington": "33",
      "Jacque Whaumbush": "31",
      "Kathryn S Huggins": "36",
      "Lisa Rhodes": "2",
      "Monica Maria Djerassi": "35",
      "Willie Jordan": "29",
      "Write In": "1",
      "ward": 27,
      "division": "All"
    },
    {
      "Candidate": "Monica Maria Djerassi",
      "Ken Washington": "34",
      "Jacque Whaumbush": "31",
      "Kathryn S Huggins": "35",
      "Lisa Rhodes": "35",
      "Monica Maria Djerassi": "1",
      "Willie Jordan": "31",
      "Write In": "0",
      "ward": 27,
      "division": "All"
    },
    {
      "Candidate": "Willie Jordan",
      "Ken Washington": "30",
      "Jacque Whaumbush": "28",
      "Kathryn S Huggins": "29",
      "Lisa Rhodes": "29",
      "Monica Maria Djerassi": "31",
      "Willie Jordan": "1",
      "Write In": "0",
      "ward": 27,
      "division": "All"
    },
    {
      "Candidate": "Write In",
      "Ken Washington": "1",
      "Jacque Whaumbush": "0",
      "Kathryn S Huggins": "0",
      "Lisa Rhodes": "1",
      "Monica Maria Djerassi": "0",
      "Willie Jordan": "0",
      "Write In": "0",
      "ward": 27,
      "division": "All"
    },
    {
      "Candidate": "Total",
      "Ken Washington": "53",
      "Jacque Whaumbush": "41",
      "Kathryn S Huggins": "40",
      "Lisa Rhodes": "40",
      "Monica Maria Djerassi": "39",
      "Willie Jordan": "32",
      "Write In": "2",
      "ward": 27,
      "division": "All"
    }
  ],
  [
    {
      "Candidate": "",
      "Kathryn S Huggins": "Kathryn S Huggins",
      "Ken Washington": "Ken Washington",
      "Lisa Rhodes": "Lisa Rhodes",
      "Monica Maria Djerassi": "Monica Maria Djerassi",
      "Willie Jordan": "Willie Jordan",
      "Jacque Whaumbush": "Jacque Whaumbush",
      "ward": 27,
      "division": 3
    },
    {
      "Candidate": "Kathryn S Huggins",
      "Kathryn S Huggins": "1",
      "Ken Washington": "7",
      "Lisa Rhodes": "7",
      "Monica Maria Djerassi": "7",
      "Willie Jordan": "7",
      "Jacque Whaumbush": "6",
      "ward": 27,
      "division": 3
    },
    {
      "Candidate": "Ken Washington",
      "Kathryn S Huggins": "7",
      "Ken Washington": "0",
      "Lisa Rhodes": "7",
      "Monica Maria Djerassi": "7",
      "Willie Jordan": "7",
      "Jacque Whaumbush": "6",
      "ward": 27,
      "division": 3
    },
    {
      "Candidate": "Lisa Rhodes",
      "Kathryn S Huggins": "7",
      "Ken Washington": "7",
      "Lisa Rhodes": "0",
      "Monica Maria Djerassi": "7",
      "Willie Jordan": "7",
      "Jacque Whaumbush": "6",
      "ward": 27,
      "division": 3
    },
    {
      "Candidate": "Monica Maria Djerassi",
      "Kathryn S Huggins": "7",
      "Ken Washington": "7",
      "Lisa Rhodes": "7",
      "Monica Maria Djerassi": "0",
      "Willie Jordan": "7",
      "Jacque Whaumbush": "6",
      "ward": 27,
      "division": 3
    },
    {
      "Candidate": "Willie Jordan",
      "Kathryn S Huggins": "7",
      "Ken Washington": "7",
      "Lisa Rhodes": "7",
      "Monica Maria Djerassi": "7",
      "Willie Jordan": "0",
      "Jacque Whaumbush": "6",
      "ward": 27,
      "division": 3
    },
    {
      "Candidate": "Jacque Whaumbush",
      "Kathryn S Huggins": "6",
      "Ken Washington": "6",
      "Lisa Rhodes": "6",
      "Monica Maria Djerassi": "6",
      "Willie Jordan": "6",
      "Jacque Whaumbush": "0",
      "ward": 27,
      "division": 3
    },
    {
      "Candidate": "Total",
      "Kathryn S Huggins": "8",
      "Ken Washington": "7",
      "Lisa Rhodes": "7",
      "Monica Maria Djerassi": "7",
      "Willie Jordan": "7",
      "Jacque Whaumbush": "6",
      "ward": 27,
      "division": 3
    }
  ],
  [
    {
      "Candidate": "",
      "Ken Washington": "Ken Washington",
      "Jacque Whaumbush": "Jacque Whaumbush",
      "Monica Maria Djerassi": "Monica Maria Djerassi",
      "Lisa Rhodes": "Lisa Rhodes",
      "Kathryn S Huggins": "Kathryn S Huggins",
      "Willie Jordan": "Willie Jordan",
      "ward": 27,
      "division": 6
    },
    {
      "Candidate": "Ken Washington",
      "Ken Washington": "5",
      "Jacque Whaumbush": "11",
      "Monica Maria Djerassi": "11",
      "Lisa Rhodes": "10",
      "Kathryn S Huggins": "10",
      "Willie Jordan": "10",
      "ward": 27,
      "division": 6
    },
    {
      "Candidate": "Jacque Whaumbush",
      "Ken Washington": "11",
      "Jacque Whaumbush": "2",
      "Monica Maria Djerassi": "9",
      "Lisa Rhodes": "9",
      "Kathryn S Huggins": "9",
      "Willie Jordan": "9",
      "ward": 27,
      "division": 6
    },
    {
      "Candidate": "Monica Maria Djerassi",
      "Ken Washington": "11",
      "Jacque Whaumbush": "9",
      "Monica Maria Djerassi": "1",
      "Lisa Rhodes": "11",
      "Kathryn S Huggins": "11",
      "Willie Jordan": "10",
      "ward": 27,
      "division": 6
    },
    {
      "Candidate": "Lisa Rhodes",
      "Ken Washington": "10",
      "Jacque Whaumbush": "9",
      "Monica Maria Djerassi": "11",
      "Lisa Rhodes": "1",
      "Kathryn S Huggins": "11",
      "Willie Jordan": "9",
      "ward": 27,
      "division": 6
    },
    {
      "Candidate": "Kathryn S Huggins",
      "Ken Washington": "10",
      "Jacque Whaumbush": "9",
      "Monica Maria Djerassi": "11",
      "Lisa Rhodes": "11",
      "Kathryn S Huggins": "0",
      "Willie Jordan": "9",
      "ward": 27,
      "division": 6
    },
    {
      "Candidate": "Willie Jordan",
      "Ken Washington": "10",
      "Jacque Whaumbush": "9",
      "Monica Maria Djerassi": "10",
      "Lisa Rhodes": "9",
      "Kathryn S Huggins": "9",
      "Willie Jordan": "0",
      "ward": 27,
      "division": 6
    },
    {
      "Candidate": "Total",
      "Ken Washington": "18",
      "Jacque Whaumbush": "13",
      "Monica Maria Djerassi": "13",
      "Lisa Rhodes": "12",
      "Kathryn S Huggins": "11",
      "Willie Jordan": "10",
      "ward": 27,
      "division": 6
    }
  ],
  [
    {
      "Candidate": "",
      "Jacque Whaumbush": "Jacque Whaumbush",
      "Kathryn S Huggins": "Kathryn S Huggins",
      "Ken Washington": "Ken Washington",
      "Lisa Rhodes": "Lisa Rhodes",
      "Monica Maria Djerassi": "Monica Maria Djerassi",
      "Willie Jordan": "Willie Jordan",
      "Write In": "Write In",
      "ward": 27,
      "division": 11
    },
    {
      "Candidate": "Jacque Whaumbush",
      "Jacque Whaumbush": "1",
      "Kathryn S Huggins": "1",
      "Ken Washington": "1",
      "Lisa Rhodes": "1",
      "Monica Maria Djerassi": "1",
      "Willie Jordan": "1",
      "Write In": "0",
      "ward": 27,
      "division": 11
    },
    {
      "Candidate": "Kathryn S Huggins",
      "Jacque Whaumbush": "1",
      "Kathryn S Huggins": "1",
      "Ken Washington": "1",
      "Lisa Rhodes": "1",
      "Monica Maria Djerassi": "1",
      "Willie Jordan": "1",
      "Write In": "0",
      "ward": 27,
      "division": 11
    },
    {
      "Candidate": "Ken Washington",
      "Jacque Whaumbush": "1",
      "Kathryn S Huggins": "1",
      "Ken Washington": "0",
      "Lisa Rhodes": "1",
      "Monica Maria Djerassi": "2",
      "Willie Jordan": "1",
      "Write In": "0",
      "ward": 27,
      "division": 11
    },
    {
      "Candidate": "Lisa Rhodes",
      "Jacque Whaumbush": "1",
      "Kathryn S Huggins": "1",
      "Ken Washington": "1",
      "Lisa Rhodes": "0",
      "Monica Maria Djerassi": "1",
      "Willie Jordan": "1",
      "Write In": "1",
      "ward": 27,
      "division": 11
    },
    {
      "Candidate": "Monica Maria Djerassi",
      "Jacque Whaumbush": "1",
      "Kathryn S Huggins": "1",
      "Ken Washington": "2",
      "Lisa Rhodes": "1",
      "Monica Maria Djerassi": "0",
      "Willie Jordan": "1",
      "Write In": "0",
      "ward": 27,
      "division": 11
    },
    {
      "Candidate": "Willie Jordan",
      "Jacque Whaumbush": "1",
      "Kathryn S Huggins": "1",
      "Ken Washington": "1",
      "Lisa Rhodes": "1",
      "Monica Maria Djerassi": "1",
      "Willie Jordan": "0",
      "Write In": "0",
      "ward": 27,
      "division": 11
    },
    {
      "Candidate": "Write In",
      "Jacque Whaumbush": "0",
      "Kathryn S Huggins": "0",
      "Ken Washington": "0",
      "Lisa Rhodes": "1",
      "Monica Maria Djerassi": "0",
      "Willie Jordan": "0",
      "Write In": "0",
      "ward": 27,
      "division": 11
    },
    {
      "Candidate": "Total",
      "Jacque Whaumbush": "2",
      "Kathryn S Huggins": "2",
      "Ken Washington": "2",
      "Lisa Rhodes": "2",
      "Monica Maria Djerassi": "2",
      "Willie Jordan": "1",
      "Write In": "1",
      "ward": 27,
      "division": 11
    }
  ],
  [
    {
      "Candidate": "",
      "Ken Washington": "Ken Washington",
      "Jacque Whaumbush": "Jacque Whaumbush",
      "Kathryn S Huggins": "Kathryn S Huggins",
      "Lisa Rhodes": "Lisa Rhodes",
      "Monica Maria Djerassi": "Monica Maria Djerassi",
      "Willie Jordan": "Willie Jordan",
      "Write In": "Write In",
      "ward": 27,
      "division": 13
    },
    {
      "Candidate": "Ken Washington",
      "Ken Washington": "5",
      "Jacque Whaumbush": "13",
      "Kathryn S Huggins": "12",
      "Lisa Rhodes": "13",
      "Monica Maria Djerassi": "12",
      "Willie Jordan": "12",
      "Write In": "1",
      "ward": 27,
      "division": 13
    },
    {
      "Candidate": "Jacque Whaumbush",
      "Ken Washington": "13",
      "Jacque Whaumbush": "3",
      "Kathryn S Huggins": "13",
      "Lisa Rhodes": "13",
      "Monica Maria Djerassi": "13",
      "Willie Jordan": "12",
      "Write In": "0",
      "ward": 27,
      "division": 13
    },
    {
      "Candidate": "Kathryn S Huggins",
      "Ken Washington": "12",
      "Jacque Whaumbush": "13",
      "Kathryn S Huggins": "2",
      "Lisa Rhodes": "14",
      "Monica Maria Djerassi": "13",
      "Willie Jordan": "12",
      "Write In": "0",
      "ward": 27,
      "division": 13
    },
    {
      "Candidate": "Lisa Rhodes",
      "Ken Washington": "13",
      "Jacque Whaumbush": "13",
      "Kathryn S Huggins": "14",
      "Lisa Rhodes": "1",
      "Monica Maria Djerassi": "13",
      "Willie Jordan": "12",
      "Write In": "0",
      "ward": 27,
      "division": 13
    },
    {
      "Candidate": "Monica Maria Djerassi",
      "Ken Washington": "12",
      "Jacque Whaumbush": "13",
      "Kathryn S Huggins": "13",
      "Lisa Rhodes": "13",
      "Monica Maria Djerassi": "0",
      "Willie Jordan": "13",
      "Write In": "0",
      "ward": 27,
      "division": 13
    },
    {
      "Candidate": "Willie Jordan",
      "Ken Washington": "12",
      "Jacque Whaumbush": "12",
      "Kathryn S Huggins": "12",
      "Lisa Rhodes": "12",
      "Monica Maria Djerassi": "13",
      "Willie Jordan": "1",
      "Write In": "0",
      "ward": 27,
      "division": 13
    },
    {
      "Candidate": "Write In",
      "Ken Washington": "1",
      "Jacque Whaumbush": "0",
      "Kathryn S Huggins": "0",
      "Lisa Rhodes": "0",
      "Monica Maria Djerassi": "0",
      "Willie Jordan": "0",
      "Write In": "0",
      "ward": 27,
      "division": 13
    },
    {
      "Candidate": "Total",
      "Ken Washington": "22",
      "Jacque Whaumbush": "18",
      "Kathryn S Huggins": "16",
      "Lisa Rhodes": "16",
      "Monica Maria Djerassi": "14",
      "Willie Jordan": "14",
      "Write In": "1",
      "ward": 27,
      "division": 13
    }
  ],
  [
    {
      "Candidate": "",
      "Ken Washington": "Ken Washington",
      "Kathryn S Huggins": "Kathryn S Huggins",
      "Lisa Rhodes": "Lisa Rhodes",
      "Monica Maria Djerassi": "Monica Maria Djerassi",
      "Jacque Whaumbush": "Jacque Whaumbush",
      "ward": 27,
      "division": 18
    },
    {
      "Candidate": "Ken Washington",
      "Ken Washington": "2",
      "Kathryn S Huggins": "2",
      "Lisa Rhodes": "2",
      "Monica Maria Djerassi": "2",
      "Jacque Whaumbush": "2",
      "ward": 27,
      "division": 18
    },
    {
      "Candidate": "Kathryn S Huggins",
      "Ken Washington": "2",
      "Kathryn S Huggins": "0",
      "Lisa Rhodes": "3",
      "Monica Maria Djerassi": "3",
      "Jacque Whaumbush": "2",
      "ward": 27,
      "division": 18
    },
    {
      "Candidate": "Lisa Rhodes",
      "Ken Washington": "2",
      "Kathryn S Huggins": "3",
      "Lisa Rhodes": "0",
      "Monica Maria Djerassi": "3",
      "Jacque Whaumbush": "2",
      "ward": 27,
      "division": 18
    },
    {
      "Candidate": "Monica Maria Djerassi",
      "Ken Washington": "2",
      "Kathryn S Huggins": "3",
      "Lisa Rhodes": "3",
      "Monica Maria Djerassi": "0",
      "Jacque Whaumbush": "2",
      "ward": 27,
      "division": 18
    },
    {
      "Candidate": "Jacque Whaumbush",
      "Ken Washington": "2",
      "Kathryn S Huggins": "2",
      "Lisa Rhodes": "2",
      "Monica Maria Djerassi": "2",
      "Jacque Whaumbush": "0",
      "ward": 27,
      "division": 18
    },
    {
      "Candidate": "Total",
      "Ken Washington": "4",
      "Kathryn S Huggins": "3",
      "Lisa Rhodes": "3",
      "Monica Maria Djerassi": "3",
      "Jacque Whaumbush": "2",
      "ward": 27,
      "division": 18
    }
  ]
]
