[
  [
    {
      "Candidate": "",
      "Bob Casey Jr": "Bob Casey Jr",
      "Joseph John Vodvarka": "Joseph John Vodvarka",
      "ward": 15,
      "division": "All"
    },
    {
      "Candidate": "Bob Casey Jr",
      "Bob Casey Jr": "1,869",
      "Joseph John Vodvarka": "0",
      "ward": 15,
      "division": "All"
    },
    {
      "Candidate": "Joseph John Vodvarka",
      "Bob Casey Jr": "",
      "Joseph John Vodvarka": "270",
      "ward": 15,
      "division": "All"
    },
    {
      "Candidate": "Total",
      "Bob Casey Jr": "1,869",
      "Joseph John Vodvarka": "270",
      "ward": 15,
      "division": "All"
    }
  ],
  [
    {
      "Candidate": "",
      "Bob Casey Jr": "Bob Casey Jr",
      "Joseph John Vodvarka": "Joseph John Vodvarka",
      "ward": 15,
      "division": 1
    },
    {
      "Candidate": "Bob Casey Jr",
      "Bob Casey Jr": "139",
      "Joseph John Vodvarka": "0",
      "ward": 15,
      "division": 1
    },
    {
      "Candidate": "Joseph John Vodvarka",
      "Bob Casey Jr": "",
      "Joseph John Vodvarka": "12",
      "ward": 15,
      "division": 1
    },
    {
      "Candidate": "Total",
      "Bob Casey Jr": "139",
      "Joseph John Vodvarka": "12",
      "ward": 15,
      "division": 1
    }
  ],
  [
    {
      "Candidate": "",
      "Bob Casey Jr": "Bob Casey Jr",
      "Joseph John Vodvarka": "Joseph John Vodvarka",
      "ward": 15,
      "division": 2
    },
    {
      "Candidate": "Bob Casey Jr",
      "Bob Casey Jr": "116",
      "Joseph John Vodvarka": "0",
      "ward": 15,
      "division": 2
    },
    {
      "Candidate": "Joseph John Vodvarka",
      "Bob Casey Jr": "",
      "Joseph John Vodvarka": "10",
      "ward": 15,
      "division": 2
    },
    {
      "Candidate": "Total",
      "Bob Casey Jr": "116",
      "Joseph John Vodvarka": "10",
      "ward": 15,
      "division": 2
    }
  ],
  [
    {
      "Candidate": "",
      "Bob Casey Jr": "Bob Casey Jr",
      "Joseph John Vodvarka": "Joseph John Vodvarka",
      "ward": 15,
      "division": 3
    },
    {
      "Candidate": "Bob Casey Jr",
      "Bob Casey Jr": "67",
      "Joseph John Vodvarka": "0",
      "ward": 15,
      "division": 3
    },
    {
      "Candidate": "Joseph John Vodvarka",
      "Bob Casey Jr": "",
      "Joseph John Vodvarka": "7",
      "ward": 15,
      "division": 3
    },
    {
      "Candidate": "Total",
      "Bob Casey Jr": "67",
      "Joseph John Vodvarka": "7",
      "ward": 15,
      "division": 3
    }
  ],
  [
    {
      "Candidate": "",
      "Bob Casey Jr": "Bob Casey Jr",
      "Joseph John Vodvarka": "Joseph John Vodvarka",
      "ward": 15,
      "division": 4
    },
    {
      "Candidate": "Bob Casey Jr",
      "Bob Casey Jr": "63",
      "Joseph John Vodvarka": "0",
      "ward": 15,
      "division": 4
    },
    {
      "Candidate": "Joseph John Vodvarka",
      "Bob Casey Jr": "",
      "Joseph John Vodvarka": "9",
      "ward": 15,
      "division": 4
    },
    {
      "Candidate": "Total",
      "Bob Casey Jr": "63",
      "Joseph John Vodvarka": "9",
      "ward": 15,
      "division": 4
    }
  ],
  [
    {
      "Candidate": "",
      "Bob Casey Jr": "Bob Casey Jr",
      "Joseph John Vodvarka": "Joseph John Vodvarka",
      "ward": 15,
      "division": 5
    },
    {
      "Candidate": "Bob Casey Jr",
      "Bob Casey Jr": "98",
      "Joseph John Vodvarka": "0",
      "ward": 15,
      "division": 5
    },
    {
      "Candidate": "Joseph John Vodvarka",
      "Bob Casey Jr": "",
      "Joseph John Vodvarka": "15",
      "ward": 15,
      "division": 5
    },
    {
      "Candidate": "Total",
      "Bob Casey Jr": "98",
      "Joseph John Vodvarka": "15",
      "ward": 15,
      "division": 5
    }
  ],
  [
    {
      "Candidate": "",
      "Bob Casey Jr": "Bob Casey Jr",
      "Joseph John Vodvarka": "Joseph John Vodvarka",
      "ward": 15,
      "division": 6
    },
    {
      "Candidate": "Bob Casey Jr",
      "Bob Casey Jr": "200",
      "Joseph John Vodvarka": "0",
      "ward": 15,
      "division": 6
    },
    {
      "Candidate": "Joseph John Vodvarka",
      "Bob Casey Jr": "",
      "Joseph John Vodvarka": "35",
      "ward": 15,
      "division": 6
    },
    {
      "Candidate": "Total",
      "Bob Casey Jr": "200",
      "Joseph John Vodvarka": "35",
      "ward": 15,
      "division": 6
    }
  ],
  [
    {
      "Candidate": "",
      "Bob Casey Jr": "Bob Casey Jr",
      "Joseph John Vodvarka": "Joseph John Vodvarka",
      "ward": 15,
      "division": 7
    },
    {
      "Candidate": "Bob Casey Jr",
      "Bob Casey Jr": "82",
      "Joseph John Vodvarka": "0",
      "ward": 15,
      "division": 7
    },
    {
      "Candidate": "Joseph John Vodvarka",
      "Bob Casey Jr": "",
      "Joseph John Vodvarka": "18",
      "ward": 15,
      "division": 7
    },
    {
      "Candidate": "Total",
      "Bob Casey Jr": "82",
      "Joseph John Vodvarka": "18",
      "ward": 15,
      "division": 7
    }
  ],
  [
    {
      "Candidate": "",
      "Bob Casey Jr": "Bob Casey Jr",
      "Joseph John Vodvarka": "Joseph John Vodvarka",
      "ward": 15,
      "division": 8
    },
    {
      "Candidate": "Bob Casey Jr",
      "Bob Casey Jr": "75",
      "Joseph John Vodvarka": "0",
      "ward": 15,
      "division": 8
    },
    {
      "Candidate": "Joseph John Vodvarka",
      "Bob Casey Jr": "",
      "Joseph John Vodvarka": "10",
      "ward": 15,
      "division": 8
    },
    {
      "Candidate": "Total",
      "Bob Casey Jr": "75",
      "Joseph John Vodvarka": "10",
      "ward": 15,
      "division": 8
    }
  ],
  [
    {
      "Candidate": "",
      "Bob Casey Jr": "Bob Casey Jr",
      "Joseph John Vodvarka": "Joseph John Vodvarka",
      "ward": 15,
      "division": 9
    },
    {
      "Candidate": "Bob Casey Jr",
      "Bob Casey Jr": "92",
      "Joseph John Vodvarka": "0",
      "ward": 15,
      "division": 9
    },
    {
      "Candidate": "Joseph John Vodvarka",
      "Bob Casey Jr": "",
      "Joseph John Vodvarka": "13",
      "ward": 15,
      "division": 9
    },
    {
      "Candidate": "Total",
      "Bob Casey Jr": "92",
      "Joseph John Vodvarka": "13",
      "ward": 15,
      "division": 9
    }
  ],
  [
    {
      "Candidate": "",
      "Bob Casey Jr": "Bob Casey Jr",
      "Joseph John Vodvarka": "Joseph John Vodvarka",
      "ward": 15,
      "division": 10
    },
    {
      "Candidate": "Bob Casey Jr",
      "Bob Casey Jr": "98",
      "Joseph John Vodvarka": "0",
      "ward": 15,
      "division": 10
    },
    {
      "Candidate": "Joseph John Vodvarka",
      "Bob Casey Jr": "",
      "Joseph John Vodvarka": "15",
      "ward": 15,
      "division": 10
    },
    {
      "Candidate": "Total",
      "Bob Casey Jr": "98",
      "Joseph John Vodvarka": "15",
      "ward": 15,
      "division": 10
    }
  ],
  [
    {
      "Candidate": "",
      "Bob Casey Jr": "Bob Casey Jr",
      "Joseph John Vodvarka": "Joseph John Vodvarka",
      "ward": 15,
      "division": 11
    },
    {
      "Candidate": "Bob Casey Jr",
      "Bob Casey Jr": "90",
      "Joseph John Vodvarka": "0",
      "ward": 15,
      "division": 11
    },
    {
      "Candidate": "Joseph John Vodvarka",
      "Bob Casey Jr": "",
      "Joseph John Vodvarka": "14",
      "ward": 15,
      "division": 11
    },
    {
      "Candidate": "Total",
      "Bob Casey Jr": "90",
      "Joseph John Vodvarka": "14",
      "ward": 15,
      "division": 11
    }
  ],
  [
    {
      "Candidate": "",
      "Bob Casey Jr": "Bob Casey Jr",
      "Joseph John Vodvarka": "Joseph John Vodvarka",
      "ward": 15,
      "division": 12
    },
    {
      "Candidate": "Bob Casey Jr",
      "Bob Casey Jr": "101",
      "Joseph John Vodvarka": "0",
      "ward": 15,
      "division": 12
    },
    {
      "Candidate": "Joseph John Vodvarka",
      "Bob Casey Jr": "",
      "Joseph John Vodvarka": "21",
      "ward": 15,
      "division": 12
    },
    {
      "Candidate": "Total",
      "Bob Casey Jr": "101",
      "Joseph John Vodvarka": "21",
      "ward": 15,
      "division": 12
    }
  ],
  [
    {
      "Candidate": "",
      "Bob Casey Jr": "Bob Casey Jr",
      "Joseph John Vodvarka": "Joseph John Vodvarka",
      "ward": 15,
      "division": 13
    },
    {
      "Candidate": "Bob Casey Jr",
      "Bob Casey Jr": "78",
      "Joseph John Vodvarka": "0",
      "ward": 15,
      "division": 13
    },
    {
      "Candidate": "Joseph John Vodvarka",
      "Bob Casey Jr": "",
      "Joseph John Vodvarka": "21",
      "ward": 15,
      "division": 13
    },
    {
      "Candidate": "Total",
      "Bob Casey Jr": "78",
      "Joseph John Vodvarka": "21",
      "ward": 15,
      "division": 13
    }
  ],
  [
    {
      "Candidate": "",
      "Bob Casey Jr": "Bob Casey Jr",
      "Joseph John Vodvarka": "Joseph John Vodvarka",
      "ward": 15,
      "division": 14
    },
    {
      "Candidate": "Bob Casey Jr",
      "Bob Casey Jr": "105",
      "Joseph John Vodvarka": "0",
      "ward": 15,
      "division": 14
    },
    {
      "Candidate": "Joseph John Vodvarka",
      "Bob Casey Jr": "",
      "Joseph John Vodvarka": "12",
      "ward": 15,
      "division": 14
    },
    {
      "Candidate": "Total",
      "Bob Casey Jr": "105",
      "Joseph John Vodvarka": "12",
      "ward": 15,
      "division": 14
    }
  ],
  [
    {
      "Candidate": "",
      "Bob Casey Jr": "Bob Casey Jr",
      "Joseph John Vodvarka": "Joseph John Vodvarka",
      "ward": 15,
      "division": 15
    },
    {
      "Candidate": "Bob Casey Jr",
      "Bob Casey Jr": "54",
      "Joseph John Vodvarka": "0",
      "ward": 15,
      "division": 15
    },
    {
      "Candidate": "Joseph John Vodvarka",
      "Bob Casey Jr": "",
      "Joseph John Vodvarka": "11",
      "ward": 15,
      "division": 15
    },
    {
      "Candidate": "Total",
      "Bob Casey Jr": "54",
      "Joseph John Vodvarka": "11",
      "ward": 15,
      "division": 15
    }
  ],
  [
    {
      "Candidate": "",
      "Bob Casey Jr": "Bob Casey Jr",
      "Joseph John Vodvarka": "Joseph John Vodvarka",
      "ward": 15,
      "division": 16
    },
    {
      "Candidate": "Bob Casey Jr",
      "Bob Casey Jr": "118",
      "Joseph John Vodvarka": "0",
      "ward": 15,
      "division": 16
    },
    {
      "Candidate": "Joseph John Vodvarka",
      "Bob Casey Jr": "",
      "Joseph John Vodvarka": "10",
      "ward": 15,
      "division": 16
    },
    {
      "Candidate": "Total",
      "Bob Casey Jr": "118",
      "Joseph John Vodvarka": "10",
      "ward": 15,
      "division": 16
    }
  ],
  [
    {
      "Candidate": "",
      "Bob Casey Jr": "Bob Casey Jr",
      "Joseph John Vodvarka": "Joseph John Vodvarka",
      "ward": 15,
      "division": 17
    },
    {
      "Candidate": "Bob Casey Jr",
      "Bob Casey Jr": "98",
      "Joseph John Vodvarka": "0",
      "ward": 15,
      "division": 17
    },
    {
      "Candidate": "Joseph John Vodvarka",
      "Bob Casey Jr": "",
      "Joseph John Vodvarka": "15",
      "ward": 15,
      "division": 17
    },
    {
      "Candidate": "Total",
      "Bob Casey Jr": "98",
      "Joseph John Vodvarka": "15",
      "ward": 15,
      "division": 17
    }
  ],
  [
    {
      "Candidate": "",
      "Bob Casey Jr": "Bob Casey Jr",
      "Joseph John Vodvarka": "Joseph John Vodvarka",
      "ward": 15,
      "division": 18
    },
    {
      "Candidate": "Bob Casey Jr",
      "Bob Casey Jr": "99",
      "Joseph John Vodvarka": "0",
      "ward": 15,
      "division": 18
    },
    {
      "Candidate": "Joseph John Vodvarka",
      "Bob Casey Jr": "",
      "Joseph John Vodvarka": "12",
      "ward": 15,
      "division": 18
    },
    {
      "Candidate": "Total",
      "Bob Casey Jr": "99",
      "Joseph John Vodvarka": "12",
      "ward": 15,
      "division": 18
    }
  ],
  [
    {
      "Candidate": "",
      "Bob Casey Jr": "Bob Casey Jr",
      "Joseph John Vodvarka": "Joseph John Vodvarka",
      "ward": 15,
      "division": 19
    },
    {
      "Candidate": "Bob Casey Jr",
      "Bob Casey Jr": "96",
      "Joseph John Vodvarka": "0",
      "ward": 15,
      "division": 19
    },
    {
      "Candidate": "Joseph John Vodvarka",
      "Bob Casey Jr": "",
      "Joseph John Vodvarka": "10",
      "ward": 15,
      "division": 19
    },
    {
      "Candidate": "Total",
      "Bob Casey Jr": "96",
      "Joseph John Vodvarka": "10",
      "ward": 15,
      "division": 19
    }
  ]
]
