[
  [
    {
      "Candidate": "",
      "Brendan F Boyle": "Brendan F Boyle",
      "Michele Lawrence": "Michele Lawrence",
      "Write In": "Write In",
      "ward": 49,
      "division": "All"
    },
    {
      "Candidate": "Brendan F Boyle",
      "Brendan F Boyle": "1,193",
      "Michele Lawrence": "0",
      "Write In": "0",
      "ward": 49,
      "division": "All"
    },
    {
      "Candidate": "Michele Lawrence",
      "Brendan F Boyle": "",
      "Michele Lawrence": "915",
      "Write In": "0",
      "ward": 49,
      "division": "All"
    },
    {
      "Candidate": "Write In",
      "Brendan F Boyle": "",
      "Michele Lawrence": "",
      "Write In": "1",
      "ward": 49,
      "division": "All"
    },
    {
      "Candidate": "Total",
      "Brendan F Boyle": "1,193",
      "Michele Lawrence": "915",
      "Write In": "1",
      "ward": 49,
      "division": "All"
    }
  ],
  [
    {
      "Candidate": "",
      "Michele Lawrence": "Michele Lawrence",
      "Brendan F Boyle": "Brendan F Boyle",
      "ward": 49,
      "division": 1
    },
    {
      "Candidate": "Michele Lawrence",
      "Michele Lawrence": "30",
      "Brendan F Boyle": "0",
      "ward": 49,
      "division": 1
    },
    {
      "Candidate": "Brendan F Boyle",
      "Michele Lawrence": "",
      "Brendan F Boyle": "18",
      "ward": 49,
      "division": 1
    },
    {
      "Candidate": "Total",
      "Michele Lawrence": "30",
      "Brendan F Boyle": "18",
      "ward": 49,
      "division": 1
    }
  ],
  [
    {
      "Candidate": "",
      "Brendan F Boyle": "Brendan F Boyle",
      "Michele Lawrence": "Michele Lawrence",
      "ward": 49,
      "division": 2
    },
    {
      "Candidate": "Brendan F Boyle",
      "Brendan F Boyle": "48",
      "Michele Lawrence": "0",
      "ward": 49,
      "division": 2
    },
    {
      "Candidate": "Michele Lawrence",
      "Brendan F Boyle": "",
      "Michele Lawrence": "48",
      "ward": 49,
      "division": 2
    },
    {
      "Candidate": "Total",
      "Brendan F Boyle": "48",
      "Michele Lawrence": "48",
      "ward": 49,
      "division": 2
    }
  ],
  [
    {
      "Candidate": "",
      "Brendan F Boyle": "Brendan F Boyle",
      "Michele Lawrence": "Michele Lawrence",
      "ward": 49,
      "division": 3
    },
    {
      "Candidate": "Brendan F Boyle",
      "Brendan F Boyle": "78",
      "Michele Lawrence": "0",
      "ward": 49,
      "division": 3
    },
    {
      "Candidate": "Michele Lawrence",
      "Brendan F Boyle": "",
      "Michele Lawrence": "45",
      "ward": 49,
      "division": 3
    },
    {
      "Candidate": "Total",
      "Brendan F Boyle": "78",
      "Michele Lawrence": "45",
      "ward": 49,
      "division": 3
    }
  ],
  [
    {
      "Candidate": "",
      "Brendan F Boyle": "Brendan F Boyle",
      "Michele Lawrence": "Michele Lawrence",
      "ward": 49,
      "division": 4
    },
    {
      "Candidate": "Brendan F Boyle",
      "Brendan F Boyle": "41",
      "Michele Lawrence": "0",
      "ward": 49,
      "division": 4
    },
    {
      "Candidate": "Michele Lawrence",
      "Brendan F Boyle": "",
      "Michele Lawrence": "30",
      "ward": 49,
      "division": 4
    },
    {
      "Candidate": "Total",
      "Brendan F Boyle": "41",
      "Michele Lawrence": "30",
      "ward": 49,
      "division": 4
    }
  ],
  [
    {
      "Candidate": "",
      "Michele Lawrence": "Michele Lawrence",
      "Brendan F Boyle": "Brendan F Boyle",
      "ward": 49,
      "division": 5
    },
    {
      "Candidate": "Michele Lawrence",
      "Michele Lawrence": "67",
      "Brendan F Boyle": "0",
      "ward": 49,
      "division": 5
    },
    {
      "Candidate": "Brendan F Boyle",
      "Michele Lawrence": "",
      "Brendan F Boyle": "18",
      "ward": 49,
      "division": 5
    },
    {
      "Candidate": "Total",
      "Michele Lawrence": "67",
      "Brendan F Boyle": "18",
      "ward": 49,
      "division": 5
    }
  ],
  [
    {
      "Candidate": "",
      "Brendan F Boyle": "Brendan F Boyle",
      "Michele Lawrence": "Michele Lawrence",
      "ward": 49,
      "division": 6
    },
    {
      "Candidate": "Brendan F Boyle",
      "Brendan F Boyle": "74",
      "Michele Lawrence": "0",
      "ward": 49,
      "division": 6
    },
    {
      "Candidate": "Michele Lawrence",
      "Brendan F Boyle": "",
      "Michele Lawrence": "60",
      "ward": 49,
      "division": 6
    },
    {
      "Candidate": "Total",
      "Brendan F Boyle": "74",
      "Michele Lawrence": "60",
      "ward": 49,
      "division": 6
    }
  ],
  [
    {
      "Candidate": "",
      "Brendan F Boyle": "Brendan F Boyle",
      "Michele Lawrence": "Michele Lawrence",
      "ward": 49,
      "division": 7
    },
    {
      "Candidate": "Brendan F Boyle",
      "Brendan F Boyle": "60",
      "Michele Lawrence": "0",
      "ward": 49,
      "division": 7
    },
    {
      "Candidate": "Michele Lawrence",
      "Brendan F Boyle": "",
      "Michele Lawrence": "40",
      "ward": 49,
      "division": 7
    },
    {
      "Candidate": "Total",
      "Brendan F Boyle": "60",
      "Michele Lawrence": "40",
      "ward": 49,
      "division": 7
    }
  ],
  [
    {
      "Candidate": "",
      "Brendan F Boyle": "Brendan F Boyle",
      "Michele Lawrence": "Michele Lawrence",
      "ward": 49,
      "division": 8
    },
    {
      "Candidate": "Brendan F Boyle",
      "Brendan F Boyle": "84",
      "Michele Lawrence": "0",
      "ward": 49,
      "division": 8
    },
    {
      "Candidate": "Michele Lawrence",
      "Brendan F Boyle": "",
      "Michele Lawrence": "67",
      "ward": 49,
      "division": 8
    },
    {
      "Candidate": "Total",
      "Brendan F Boyle": "84",
      "Michele Lawrence": "67",
      "ward": 49,
      "division": 8
    }
  ],
  [
    {
      "Candidate": "",
      "Brendan F Boyle": "Brendan F Boyle",
      "Michele Lawrence": "Michele Lawrence",
      "ward": 49,
      "division": 9
    },
    {
      "Candidate": "Brendan F Boyle",
      "Brendan F Boyle": "66",
      "Michele Lawrence": "0",
      "ward": 49,
      "division": 9
    },
    {
      "Candidate": "Michele Lawrence",
      "Brendan F Boyle": "",
      "Michele Lawrence": "46",
      "ward": 49,
      "division": 9
    },
    {
      "Candidate": "Total",
      "Brendan F Boyle": "66",
      "Michele Lawrence": "46",
      "ward": 49,
      "division": 9
    }
  ],
  [
    {
      "Candidate": "",
      "Brendan F Boyle": "Brendan F Boyle",
      "Michele Lawrence": "Michele Lawrence",
      "ward": 49,
      "division": 10
    },
    {
      "Candidate": "Brendan F Boyle",
      "Brendan F Boyle": "63",
      "Michele Lawrence": "0",
      "ward": 49,
      "division": 10
    },
    {
      "Candidate": "Michele Lawrence",
      "Brendan F Boyle": "",
      "Michele Lawrence": "26",
      "ward": 49,
      "division": 10
    },
    {
      "Candidate": "Total",
      "Brendan F Boyle": "63",
      "Michele Lawrence": "26",
      "ward": 49,
      "division": 10
    }
  ],
  [
    {
      "Candidate": "",
      "Michele Lawrence": "Michele Lawrence",
      "Brendan F Boyle": "Brendan F Boyle",
      "ward": 49,
      "division": 11
    },
    {
      "Candidate": "Michele Lawrence",
      "Michele Lawrence": "58",
      "Brendan F Boyle": "0",
      "ward": 49,
      "division": 11
    },
    {
      "Candidate": "Brendan F Boyle",
      "Michele Lawrence": "",
      "Brendan F Boyle": "17",
      "ward": 49,
      "division": 11
    },
    {
      "Candidate": "Total",
      "Michele Lawrence": "58",
      "Brendan F Boyle": "17",
      "ward": 49,
      "division": 11
    }
  ],
  [
    {
      "Candidate": "",
      "Brendan F Boyle": "Brendan F Boyle",
      "Michele Lawrence": "Michele Lawrence",
      "ward": 49,
      "division": 12
    },
    {
      "Candidate": "Brendan F Boyle",
      "Brendan F Boyle": "31",
      "Michele Lawrence": "0",
      "ward": 49,
      "division": 12
    },
    {
      "Candidate": "Michele Lawrence",
      "Brendan F Boyle": "",
      "Michele Lawrence": "30",
      "ward": 49,
      "division": 12
    },
    {
      "Candidate": "Total",
      "Brendan F Boyle": "31",
      "Michele Lawrence": "30",
      "ward": 49,
      "division": 12
    }
  ],
  [
    {
      "Candidate": "",
      "Michele Lawrence": "Michele Lawrence",
      "Brendan F Boyle": "Brendan F Boyle",
      "ward": 49,
      "division": 13
    },
    {
      "Candidate": "Michele Lawrence",
      "Michele Lawrence": "19",
      "Brendan F Boyle": "0",
      "ward": 49,
      "division": 13
    },
    {
      "Candidate": "Brendan F Boyle",
      "Michele Lawrence": "",
      "Brendan F Boyle": "12",
      "ward": 49,
      "division": 13
    },
    {
      "Candidate": "Total",
      "Michele Lawrence": "19",
      "Brendan F Boyle": "12",
      "ward": 49,
      "division": 13
    }
  ],
  [
    {
      "Candidate": "",
      "Brendan F Boyle": "Brendan F Boyle",
      "Michele Lawrence": "Michele Lawrence",
      "ward": 49,
      "division": 14
    },
    {
      "Candidate": "Brendan F Boyle",
      "Brendan F Boyle": "40",
      "Michele Lawrence": "0",
      "ward": 49,
      "division": 14
    },
    {
      "Candidate": "Michele Lawrence",
      "Brendan F Boyle": "",
      "Michele Lawrence": "35",
      "ward": 49,
      "division": 14
    },
    {
      "Candidate": "Total",
      "Brendan F Boyle": "40",
      "Michele Lawrence": "35",
      "ward": 49,
      "division": 14
    }
  ],
  [
    {
      "Candidate": "",
      "Brendan F Boyle": "Brendan F Boyle",
      "Michele Lawrence": "Michele Lawrence",
      "ward": 49,
      "division": 15
    },
    {
      "Candidate": "Brendan F Boyle",
      "Brendan F Boyle": "52",
      "Michele Lawrence": "0",
      "ward": 49,
      "division": 15
    },
    {
      "Candidate": "Michele Lawrence",
      "Brendan F Boyle": "",
      "Michele Lawrence": "11",
      "ward": 49,
      "division": 15
    },
    {
      "Candidate": "Total",
      "Brendan F Boyle": "52",
      "Michele Lawrence": "11",
      "ward": 49,
      "division": 15
    }
  ],
  [
    {
      "Candidate": "",
      "Brendan F Boyle": "Brendan F Boyle",
      "Michele Lawrence": "Michele Lawrence",
      "ward": 49,
      "division": 16
    },
    {
      "Candidate": "Brendan F Boyle",
      "Brendan F Boyle": "67",
      "Michele Lawrence": "0",
      "ward": 49,
      "division": 16
    },
    {
      "Candidate": "Michele Lawrence",
      "Brendan F Boyle": "",
      "Michele Lawrence": "25",
      "ward": 49,
      "division": 16
    },
    {
      "Candidate": "Total",
      "Brendan F Boyle": "67",
      "Michele Lawrence": "25",
      "ward": 49,
      "division": 16
    }
  ],
  [
    {
      "Candidate": "",
      "Brendan F Boyle": "Brendan F Boyle",
      "Michele Lawrence": "Michele Lawrence",
      "ward": 49,
      "division": 17
    },
    {
      "Candidate": "Brendan F Boyle",
      "Brendan F Boyle": "56",
      "Michele Lawrence": "0",
      "ward": 49,
      "division": 17
    },
    {
      "Candidate": "Michele Lawrence",
      "Brendan F Boyle": "",
      "Michele Lawrence": "40",
      "ward": 49,
      "division": 17
    },
    {
      "Candidate": "Total",
      "Brendan F Boyle": "56",
      "Michele Lawrence": "40",
      "ward": 49,
      "division": 17
    }
  ],
  [
    {
      "Candidate": "",
      "Brendan F Boyle": "Brendan F Boyle",
      "Michele Lawrence": "Michele Lawrence",
      "Write In": "Write In",
      "ward": 49,
      "division": 18
    },
    {
      "Candidate": "Brendan F Boyle",
      "Brendan F Boyle": "82",
      "Michele Lawrence": "0",
      "Write In": "0",
      "ward": 49,
      "division": 18
    },
    {
      "Candidate": "Michele Lawrence",
      "Brendan F Boyle": "",
      "Michele Lawrence": "53",
      "Write In": "0",
      "ward": 49,
      "division": 18
    },
    {
      "Candidate": "Write In",
      "Brendan F Boyle": "",
      "Michele Lawrence": "",
      "Write In": "1",
      "ward": 49,
      "division": 18
    },
    {
      "Candidate": "Total",
      "Brendan F Boyle": "82",
      "Michele Lawrence": "53",
      "Write In": "1",
      "ward": 49,
      "division": 18
    }
  ],
  [
    {
      "Candidate": "",
      "Brendan F Boyle": "Brendan F Boyle",
      "Michele Lawrence": "Michele Lawrence",
      "ward": 49,
      "division": 19
    },
    {
      "Candidate": "Brendan F Boyle",
      "Brendan F Boyle": "60",
      "Michele Lawrence": "0",
      "ward": 49,
      "division": 19
    },
    {
      "Candidate": "Michele Lawrence",
      "Brendan F Boyle": "",
      "Michele Lawrence": "28",
      "ward": 49,
      "division": 19
    },
    {
      "Candidate": "Total",
      "Brendan F Boyle": "60",
      "Michele Lawrence": "28",
      "ward": 49,
      "division": 19
    }
  ],
  [
    {
      "Candidate": "",
      "Brendan F Boyle": "Brendan F Boyle",
      "Michele Lawrence": "Michele Lawrence",
      "ward": 49,
      "division": 20
    },
    {
      "Candidate": "Brendan F Boyle",
      "Brendan F Boyle": "73",
      "Michele Lawrence": "0",
      "ward": 49,
      "division": 20
    },
    {
      "Candidate": "Michele Lawrence",
      "Brendan F Boyle": "",
      "Michele Lawrence": "44",
      "ward": 49,
      "division": 20
    },
    {
      "Candidate": "Total",
      "Brendan F Boyle": "73",
      "Michele Lawrence": "44",
      "ward": 49,
      "division": 20
    }
  ],
  [
    {
      "Candidate": "",
      "Brendan F Boyle": "Brendan F Boyle",
      "Michele Lawrence": "Michele Lawrence",
      "ward": 49,
      "division": 21
    },
    {
      "Candidate": "Brendan F Boyle",
      "Brendan F Boyle": "97",
      "Michele Lawrence": "0",
      "ward": 49,
      "division": 21
    },
    {
      "Candidate": "Michele Lawrence",
      "Brendan F Boyle": "",
      "Michele Lawrence": "53",
      "ward": 49,
      "division": 21
    },
    {
      "Candidate": "Total",
      "Brendan F Boyle": "97",
      "Michele Lawrence": "53",
      "ward": 49,
      "division": 21
    }
  ],
  [
    {
      "Candidate": "",
      "Michele Lawrence": "Michele Lawrence",
      "Brendan F Boyle": "Brendan F Boyle",
      "ward": 49,
      "division": 22
    },
    {
      "Candidate": "Michele Lawrence",
      "Michele Lawrence": "60",
      "Brendan F Boyle": "0",
      "ward": 49,
      "division": 22
    },
    {
      "Candidate": "Brendan F Boyle",
      "Michele Lawrence": "",
      "Brendan F Boyle": "56",
      "ward": 49,
      "division": 22
    },
    {
      "Candidate": "Total",
      "Michele Lawrence": "60",
      "Brendan F Boyle": "56",
      "ward": 49,
      "division": 22
    }
  ]
]
