[
  [
    {
      "Candidate": "",
      "John Rafferty": "John Rafferty",
      "Joe Peters": "Joe Peters",
      "ward": 14,
      "division": "All"
    },
    {
      "Candidate": "John Rafferty",
      "John Rafferty": "16",
      "Joe Peters": "0",
      "ward": 14,
      "division": "All"
    },
    {
      "Candidate": "Joe Peters",
      "John Rafferty": "0",
      "Joe Peters": "12",
      "ward": 14,
      "division": "All"
    },
    {
      "Candidate": "Total",
      "John Rafferty": "16",
      "Joe Peters": "12",
      "ward": 14,
      "division": "All"
    }
  ],
  [
    {
      "Candidate": "",
      "John Rafferty": "John Rafferty",
      "Joe Peters": "Joe Peters",
      "ward": 14,
      "division": 1
    },
    {
      "Candidate": "John Rafferty",
      "John Rafferty": "7",
      "Joe Peters": "0",
      "ward": 14,
      "division": 1
    },
    {
      "Candidate": "Joe Peters",
      "John Rafferty": "0",
      "Joe Peters": "4",
      "ward": 14,
      "division": 1
    },
    {
      "Candidate": "Total",
      "John Rafferty": "7",
      "Joe Peters": "4",
      "ward": 14,
      "division": 1
    }
  ],
  [
    {
      "Candidate": "",
      "John Rafferty": "John Rafferty",
      "ward": 14,
      "division": 2
    },
    {
      "Candidate": "John Rafferty",
      "John Rafferty": "1",
      "ward": 14,
      "division": 2
    },
    {
      "Candidate": "Total",
      "John Rafferty": "1",
      "ward": 14,
      "division": 2
    }
  ],
  [
    {
      "Candidate": "",
      "Joe Peters": "Joe Peters",
      "John Rafferty": "John Rafferty",
      "ward": 14,
      "division": 5
    },
    {
      "Candidate": "Joe Peters",
      "Joe Peters": "1",
      "John Rafferty": "0",
      "ward": 14,
      "division": 5
    },
    {
      "Candidate": "John Rafferty",
      "Joe Peters": "0",
      "John Rafferty": "1",
      "ward": 14,
      "division": 5
    },
    {
      "Candidate": "Total",
      "Joe Peters": "1",
      "John Rafferty": "1",
      "ward": 14,
      "division": 5
    }
  ],
  [
    {
      "Candidate": "",
      "John Rafferty": "John Rafferty",
      "ward": 14,
      "division": 7
    },
    {
      "Candidate": "John Rafferty",
      "John Rafferty": "1",
      "ward": 14,
      "division": 7
    },
    {
      "Candidate": "Total",
      "John Rafferty": "1",
      "ward": 14,
      "division": 7
    }
  ],
  [
    {
      "Candidate": "",
      "John Rafferty": "John Rafferty",
      "Joe Peters": "Joe Peters",
      "ward": 14,
      "division": 9
    },
    {
      "Candidate": "John Rafferty",
      "John Rafferty": "3",
      "Joe Peters": "0",
      "ward": 14,
      "division": 9
    },
    {
      "Candidate": "Joe Peters",
      "John Rafferty": "0",
      "Joe Peters": "1",
      "ward": 14,
      "division": 9
    },
    {
      "Candidate": "Total",
      "John Rafferty": "3",
      "Joe Peters": "1",
      "ward": 14,
      "division": 9
    }
  ],
  [
    {
      "Candidate": "",
      "Joe Peters": "Joe Peters",
      "John Rafferty": "John Rafferty",
      "ward": 14,
      "division": 10
    },
    {
      "Candidate": "Joe Peters",
      "Joe Peters": "5",
      "John Rafferty": "0",
      "ward": 14,
      "division": 10
    },
    {
      "Candidate": "John Rafferty",
      "Joe Peters": "0",
      "John Rafferty": "2",
      "ward": 14,
      "division": 10
    },
    {
      "Candidate": "Total",
      "Joe Peters": "5",
      "John Rafferty": "2",
      "ward": 14,
      "division": 10
    }
  ],
  [
    {
      "Candidate": "",
      "Joe Peters": "Joe Peters",
      "John Rafferty": "John Rafferty",
      "ward": 14,
      "division": 11
    },
    {
      "Candidate": "Joe Peters",
      "Joe Peters": "1",
      "John Rafferty": "0",
      "ward": 14,
      "division": 11
    },
    {
      "Candidate": "John Rafferty",
      "Joe Peters": "0",
      "John Rafferty": "1",
      "ward": 14,
      "division": 11
    },
    {
      "Candidate": "Total",
      "Joe Peters": "1",
      "John Rafferty": "1",
      "ward": 14,
      "division": 11
    }
  ]
]
