[
  [
    {
      "Candidate": "",
      "Kevin M Dougherty": "Kevin M Dougherty",
      "Christine Donohue": "Christine Donohue",
      "David Wecht": "David Wecht",
      "Judy Olson": "Judy Olson",
      "Anne Covey": "Anne Covey",
      "Mike George": "Mike George",
      "Paul P Panepinto": "Paul P Panepinto",
      "Write In": "Write In",
      "ward": 31,
      "division": "All"
    },
    {
      "Candidate": "Kevin M Dougherty",
      "Kevin M Dougherty": "492",
      "Christine Donohue": "1433",
      "David Wecht": "1365",
      "Judy Olson": "87",
      "Anne Covey": "65",
      "Mike George": "37",
      "Paul P Panepinto": "41",
      "Write In": "0",
      "ward": 31,
      "division": "All"
    },
    {
      "Candidate": "Christine Donohue",
      "Kevin M Dougherty": "1433",
      "Christine Donohue": "72",
      "David Wecht": "1443",
      "Judy Olson": "107",
      "Anne Covey": "30",
      "Mike George": "12",
      "Paul P Panepinto": "59",
      "Write In": "0",
      "ward": 31,
      "division": "All"
    },
    {
      "Candidate": "David Wecht",
      "Kevin M Dougherty": "1365",
      "Christine Donohue": "1443",
      "David Wecht": "45",
      "Judy Olson": "77",
      "Anne Covey": "12",
      "Mike George": "15",
      "Paul P Panepinto": "40",
      "Write In": "0",
      "ward": 31,
      "division": "All"
    },
    {
      "Candidate": "Judy Olson",
      "Kevin M Dougherty": "87",
      "Christine Donohue": "107",
      "David Wecht": "77",
      "Judy Olson": "24",
      "Anne Covey": "213",
      "Mike George": "179",
      "Paul P Panepinto": "15",
      "Write In": "0",
      "ward": 31,
      "division": "All"
    },
    {
      "Candidate": "Anne Covey",
      "Kevin M Dougherty": "65",
      "Christine Donohue": "30",
      "David Wecht": "12",
      "Judy Olson": "213",
      "Anne Covey": "6",
      "Mike George": "162",
      "Paul P Panepinto": "9",
      "Write In": "0",
      "ward": 31,
      "division": "All"
    },
    {
      "Candidate": "Mike George",
      "Kevin M Dougherty": "37",
      "Christine Donohue": "12",
      "David Wecht": "15",
      "Judy Olson": "179",
      "Anne Covey": "162",
      "Mike George": "10",
      "Paul P Panepinto": "8",
      "Write In": "0",
      "ward": 31,
      "division": "All"
    },
    {
      "Candidate": "Paul P Panepinto",
      "Kevin M Dougherty": "41",
      "Christine Donohue": "59",
      "David Wecht": "40",
      "Judy Olson": "15",
      "Anne Covey": "9",
      "Mike George": "8",
      "Paul P Panepinto": "3",
      "Write In": "0",
      "ward": 31,
      "division": "All"
    },
    {
      "Candidate": "Write In",
      "Kevin M Dougherty": "0",
      "Christine Donohue": "0",
      "David Wecht": "0",
      "Judy Olson": "0",
      "Anne Covey": "0",
      "Mike George": "0",
      "Paul P Panepinto": "0",
      "Write In": "1",
      "ward": 31,
      "division": "All"
    },
    {
      "Candidate": "Total",
      "Kevin M Dougherty": "2059",
      "Christine Donohue": "1662",
      "David Wecht": "1549",
      "Judy Olson": "373",
      "Anne Covey": "262",
      "Mike George": "222",
      "Paul P Panepinto": "93",
      "Write In": "1",
      "ward": 31,
      "division": "All"
    }
  ],
  [
    {
      "Candidate": "",
      "Christine Donohue": "Christine Donohue",
      "Kevin M Dougherty": "Kevin M Dougherty",
      "David Wecht": "David Wecht",
      "Judy Olson": "Judy Olson",
      "Anne Covey": "Anne Covey",
      "Paul P Panepinto": "Paul P Panepinto",
      "Mike George": "Mike George",
      "Write In": "Write In",
      "ward": 31,
      "division": 1
    },
    {
      "Candidate": "Christine Donohue",
      "Christine Donohue": "4",
      "Kevin M Dougherty": "67",
      "David Wecht": "69",
      "Judy Olson": "8",
      "Anne Covey": "3",
      "Paul P Panepinto": "6",
      "Mike George": "0",
      "Write In": "0",
      "ward": 31,
      "division": 1
    },
    {
      "Candidate": "Kevin M Dougherty",
      "Christine Donohue": "67",
      "Kevin M Dougherty": "11",
      "David Wecht": "60",
      "Judy Olson": "1",
      "Anne Covey": "1",
      "Paul P Panepinto": "3",
      "Mike George": "0",
      "Write In": "0",
      "ward": 31,
      "division": 1
    },
    {
      "Candidate": "David Wecht",
      "Christine Donohue": "69",
      "Kevin M Dougherty": "60",
      "David Wecht": "0",
      "Judy Olson": "5",
      "Anne Covey": "1",
      "Paul P Panepinto": "3",
      "Mike George": "1",
      "Write In": "0",
      "ward": 31,
      "division": 1
    },
    {
      "Candidate": "Judy Olson",
      "Christine Donohue": "8",
      "Kevin M Dougherty": "1",
      "David Wecht": "5",
      "Judy Olson": "0",
      "Anne Covey": "6",
      "Paul P Panepinto": "1",
      "Mike George": "5",
      "Write In": "0",
      "ward": 31,
      "division": 1
    },
    {
      "Candidate": "Anne Covey",
      "Christine Donohue": "3",
      "Kevin M Dougherty": "1",
      "David Wecht": "1",
      "Judy Olson": "6",
      "Anne Covey": "0",
      "Paul P Panepinto": "0",
      "Mike George": "5",
      "Write In": "0",
      "ward": 31,
      "division": 1
    },
    {
      "Candidate": "Paul P Panepinto",
      "Christine Donohue": "6",
      "Kevin M Dougherty": "3",
      "David Wecht": "3",
      "Judy Olson": "1",
      "Anne Covey": "0",
      "Paul P Panepinto": "1",
      "Mike George": "1",
      "Write In": "0",
      "ward": 31,
      "division": 1
    },
    {
      "Candidate": "Mike George",
      "Christine Donohue": "0",
      "Kevin M Dougherty": "0",
      "David Wecht": "1",
      "Judy Olson": "5",
      "Anne Covey": "5",
      "Paul P Panepinto": "1",
      "Mike George": "0",
      "Write In": "0",
      "ward": 31,
      "division": 1
    },
    {
      "Candidate": "Write In",
      "Christine Donohue": "0",
      "Kevin M Dougherty": "0",
      "David Wecht": "0",
      "Judy Olson": "0",
      "Anne Covey": "0",
      "Paul P Panepinto": "0",
      "Mike George": "0",
      "Write In": "1",
      "ward": 31,
      "division": 1
    },
    {
      "Candidate": "Total",
      "Christine Donohue": "83",
      "Kevin M Dougherty": "79",
      "David Wecht": "71",
      "Judy Olson": "13",
      "Anne Covey": "8",
      "Paul P Panepinto": "8",
      "Mike George": "6",
      "Write In": "1",
      "ward": 31,
      "division": 1
    }
  ],
  [
    {
      "Candidate": "",
      "Kevin M Dougherty": "Kevin M Dougherty",
      "Christine Donohue": "Christine Donohue",
      "David Wecht": "David Wecht",
      "Judy Olson": "Judy Olson",
      "Anne Covey": "Anne Covey",
      "Mike George": "Mike George",
      "ward": 31,
      "division": 2
    },
    {
      "Candidate": "Kevin M Dougherty",
      "Kevin M Dougherty": "4",
      "Christine Donohue": "24",
      "David Wecht": "23",
      "Judy Olson": "1",
      "Anne Covey": "0",
      "Mike George": "0",
      "ward": 31,
      "division": 2
    },
    {
      "Candidate": "Christine Donohue",
      "Kevin M Dougherty": "24",
      "Christine Donohue": "1",
      "David Wecht": "24",
      "Judy Olson": "1",
      "Anne Covey": "0",
      "Mike George": "0",
      "ward": 31,
      "division": 2
    },
    {
      "Candidate": "David Wecht",
      "Kevin M Dougherty": "23",
      "Christine Donohue": "24",
      "David Wecht": "2",
      "Judy Olson": "0",
      "Anne Covey": "0",
      "Mike George": "0",
      "ward": 31,
      "division": 2
    },
    {
      "Candidate": "Judy Olson",
      "Kevin M Dougherty": "1",
      "Christine Donohue": "1",
      "David Wecht": "0",
      "Judy Olson": "0",
      "Anne Covey": "3",
      "Mike George": "3",
      "ward": 31,
      "division": 2
    },
    {
      "Candidate": "Anne Covey",
      "Kevin M Dougherty": "0",
      "Christine Donohue": "0",
      "David Wecht": "0",
      "Judy Olson": "3",
      "Anne Covey": "0",
      "Mike George": "3",
      "ward": 31,
      "division": 2
    },
    {
      "Candidate": "Mike George",
      "Kevin M Dougherty": "0",
      "Christine Donohue": "0",
      "David Wecht": "0",
      "Judy Olson": "3",
      "Anne Covey": "3",
      "Mike George": "0",
      "ward": 31,
      "division": 2
    },
    {
      "Candidate": "Total",
      "Kevin M Dougherty": "28",
      "Christine Donohue": "26",
      "David Wecht": "26",
      "Judy Olson": "4",
      "Anne Covey": "3",
      "Mike George": "3",
      "ward": 31,
      "division": 2
    }
  ],
  [
    {
      "Candidate": "",
      "Kevin M Dougherty": "Kevin M Dougherty",
      "Christine Donohue": "Christine Donohue",
      "David Wecht": "David Wecht",
      "Judy Olson": "Judy Olson",
      "Anne Covey": "Anne Covey",
      "Mike George": "Mike George",
      "Paul P Panepinto": "Paul P Panepinto",
      "ward": 31,
      "division": 3
    },
    {
      "Candidate": "Kevin M Dougherty",
      "Kevin M Dougherty": "20",
      "Christine Donohue": "54",
      "David Wecht": "53",
      "Judy Olson": "4",
      "Anne Covey": "3",
      "Mike George": "1",
      "Paul P Panepinto": "2",
      "ward": 31,
      "division": 3
    },
    {
      "Candidate": "Christine Donohue",
      "Kevin M Dougherty": "54",
      "Christine Donohue": "5",
      "David Wecht": "56",
      "Judy Olson": "3",
      "Anne Covey": "0",
      "Mike George": "0",
      "Paul P Panepinto": "5",
      "ward": 31,
      "division": 3
    },
    {
      "Candidate": "David Wecht",
      "Kevin M Dougherty": "53",
      "Christine Donohue": "56",
      "David Wecht": "4",
      "Judy Olson": "1",
      "Anne Covey": "1",
      "Mike George": "0",
      "Paul P Panepinto": "2",
      "ward": 31,
      "division": 3
    },
    {
      "Candidate": "Judy Olson",
      "Kevin M Dougherty": "4",
      "Christine Donohue": "3",
      "David Wecht": "1",
      "Judy Olson": "1",
      "Anne Covey": "7",
      "Mike George": "6",
      "Paul P Panepinto": "1",
      "ward": 31,
      "division": 3
    },
    {
      "Candidate": "Anne Covey",
      "Kevin M Dougherty": "3",
      "Christine Donohue": "0",
      "David Wecht": "1",
      "Judy Olson": "7",
      "Anne Covey": "0",
      "Mike George": "5",
      "Paul P Panepinto": "0",
      "ward": 31,
      "division": 3
    },
    {
      "Candidate": "Mike George",
      "Kevin M Dougherty": "1",
      "Christine Donohue": "0",
      "David Wecht": "0",
      "Judy Olson": "6",
      "Anne Covey": "5",
      "Mike George": "1",
      "Paul P Panepinto": "0",
      "ward": 31,
      "division": 3
    },
    {
      "Candidate": "Paul P Panepinto",
      "Kevin M Dougherty": "2",
      "Christine Donohue": "5",
      "David Wecht": "2",
      "Judy Olson": "1",
      "Anne Covey": "0",
      "Mike George": "0",
      "Paul P Panepinto": "0",
      "ward": 31,
      "division": 3
    },
    {
      "Candidate": "Total",
      "Kevin M Dougherty": "79",
      "Christine Donohue": "65",
      "David Wecht": "62",
      "Judy Olson": "12",
      "Anne Covey": "8",
      "Mike George": "7",
      "Paul P Panepinto": "5",
      "ward": 31,
      "division": 3
    }
  ],
  [
    {
      "Candidate": "",
      "Kevin M Dougherty": "Kevin M Dougherty",
      "Christine Donohue": "Christine Donohue",
      "David Wecht": "David Wecht",
      "Judy Olson": "Judy Olson",
      "Anne Covey": "Anne Covey",
      "Mike George": "Mike George",
      "Paul P Panepinto": "Paul P Panepinto",
      "ward": 31,
      "division": 4
    },
    {
      "Candidate": "Kevin M Dougherty",
      "Kevin M Dougherty": "18",
      "Christine Donohue": "128",
      "David Wecht": "123",
      "Judy Olson": "11",
      "Anne Covey": "5",
      "Mike George": "5",
      "Paul P Panepinto": "6",
      "ward": 31,
      "division": 4
    },
    {
      "Candidate": "Christine Donohue",
      "Kevin M Dougherty": "128",
      "Christine Donohue": "2",
      "David Wecht": "124",
      "Judy Olson": "8",
      "Anne Covey": "2",
      "Mike George": "1",
      "Paul P Panepinto": "4",
      "ward": 31,
      "division": 4
    },
    {
      "Candidate": "David Wecht",
      "Kevin M Dougherty": "123",
      "Christine Donohue": "124",
      "David Wecht": "1",
      "Judy Olson": "8",
      "Anne Covey": "0",
      "Mike George": "1",
      "Paul P Panepinto": "1",
      "ward": 31,
      "division": 4
    },
    {
      "Candidate": "Judy Olson",
      "Kevin M Dougherty": "11",
      "Christine Donohue": "8",
      "David Wecht": "8",
      "Judy Olson": "4",
      "Anne Covey": "22",
      "Mike George": "22",
      "Paul P Panepinto": "3",
      "ward": 31,
      "division": 4
    },
    {
      "Candidate": "Anne Covey",
      "Kevin M Dougherty": "5",
      "Christine Donohue": "2",
      "David Wecht": "0",
      "Judy Olson": "22",
      "Anne Covey": "0",
      "Mike George": "20",
      "Paul P Panepinto": "0",
      "ward": 31,
      "division": 4
    },
    {
      "Candidate": "Mike George",
      "Kevin M Dougherty": "5",
      "Christine Donohue": "1",
      "David Wecht": "1",
      "Judy Olson": "22",
      "Anne Covey": "20",
      "Mike George": "0",
      "Paul P Panepinto": "1",
      "ward": 31,
      "division": 4
    },
    {
      "Candidate": "Paul P Panepinto",
      "Kevin M Dougherty": "6",
      "Christine Donohue": "4",
      "David Wecht": "1",
      "Judy Olson": "3",
      "Anne Covey": "0",
      "Mike George": "1",
      "Paul P Panepinto": "0",
      "ward": 31,
      "division": 4
    },
    {
      "Candidate": "Total",
      "Kevin M Dougherty": "161",
      "Christine Donohue": "138",
      "David Wecht": "130",
      "Judy Olson": "42",
      "Anne Covey": "25",
      "Mike George": "25",
      "Paul P Panepinto": "8",
      "ward": 31,
      "division": 4
    }
  ],
  [
    {
      "Candidate": "",
      "Kevin M Dougherty": "Kevin M Dougherty",
      "Christine Donohue": "Christine Donohue",
      "David Wecht": "David Wecht",
      "Judy Olson": "Judy Olson",
      "Anne Covey": "Anne Covey",
      "Mike George": "Mike George",
      "Paul P Panepinto": "Paul P Panepinto",
      "ward": 31,
      "division": 5
    },
    {
      "Candidate": "Kevin M Dougherty",
      "Kevin M Dougherty": "22",
      "Christine Donohue": "109",
      "David Wecht": "107",
      "Judy Olson": "0",
      "Anne Covey": "2",
      "Mike George": "2",
      "Paul P Panepinto": "0",
      "ward": 31,
      "division": 5
    },
    {
      "Candidate": "Christine Donohue",
      "Kevin M Dougherty": "109",
      "Christine Donohue": "6",
      "David Wecht": "117",
      "Judy Olson": "9",
      "Anne Covey": "2",
      "Mike George": "0",
      "Paul P Panepinto": "3",
      "ward": 31,
      "division": 5
    },
    {
      "Candidate": "David Wecht",
      "Kevin M Dougherty": "107",
      "Christine Donohue": "117",
      "David Wecht": "6",
      "Judy Olson": "7",
      "Anne Covey": "0",
      "Mike George": "0",
      "Paul P Panepinto": "3",
      "ward": 31,
      "division": 5
    },
    {
      "Candidate": "Judy Olson",
      "Kevin M Dougherty": "0",
      "Christine Donohue": "9",
      "David Wecht": "7",
      "Judy Olson": "1",
      "Anne Covey": "6",
      "Mike George": "5",
      "Paul P Panepinto": "0",
      "ward": 31,
      "division": 5
    },
    {
      "Candidate": "Anne Covey",
      "Kevin M Dougherty": "2",
      "Christine Donohue": "2",
      "David Wecht": "0",
      "Judy Olson": "6",
      "Anne Covey": "0",
      "Mike George": "5",
      "Paul P Panepinto": "0",
      "ward": 31,
      "division": 5
    },
    {
      "Candidate": "Mike George",
      "Kevin M Dougherty": "2",
      "Christine Donohue": "0",
      "David Wecht": "0",
      "Judy Olson": "5",
      "Anne Covey": "5",
      "Mike George": "1",
      "Paul P Panepinto": "0",
      "ward": 31,
      "division": 5
    },
    {
      "Candidate": "Paul P Panepinto",
      "Kevin M Dougherty": "0",
      "Christine Donohue": "3",
      "David Wecht": "3",
      "Judy Olson": "0",
      "Anne Covey": "0",
      "Mike George": "0",
      "Paul P Panepinto": "0",
      "ward": 31,
      "division": 5
    },
    {
      "Candidate": "Total",
      "Kevin M Dougherty": "136",
      "Christine Donohue": "129",
      "David Wecht": "125",
      "Judy Olson": "15",
      "Anne Covey": "8",
      "Mike George": "8",
      "Paul P Panepinto": "3",
      "ward": 31,
      "division": 5
    }
  ],
  [
    {
      "Candidate": "",
      "Kevin M Dougherty": "Kevin M Dougherty",
      "Christine Donohue": "Christine Donohue",
      "David Wecht": "David Wecht",
      "Judy Olson": "Judy Olson",
      "Mike George": "Mike George",
      "Anne Covey": "Anne Covey",
      "Paul P Panepinto": "Paul P Panepinto",
      "ward": 31,
      "division": 6
    },
    {
      "Candidate": "Kevin M Dougherty",
      "Kevin M Dougherty": "27",
      "Christine Donohue": "65",
      "David Wecht": "67",
      "Judy Olson": "6",
      "Mike George": "4",
      "Anne Covey": "3",
      "Paul P Panepinto": "1",
      "ward": 31,
      "division": 6
    },
    {
      "Candidate": "Christine Donohue",
      "Kevin M Dougherty": "65",
      "Christine Donohue": "4",
      "David Wecht": "70",
      "Judy Olson": "7",
      "Mike George": "2",
      "Anne Covey": "1",
      "Paul P Panepinto": "2",
      "ward": 31,
      "division": 6
    },
    {
      "Candidate": "David Wecht",
      "Kevin M Dougherty": "67",
      "Christine Donohue": "70",
      "David Wecht": "3",
      "Judy Olson": "8",
      "Mike George": "3",
      "Anne Covey": "0",
      "Paul P Panepinto": "3",
      "ward": 31,
      "division": 6
    },
    {
      "Candidate": "Judy Olson",
      "Kevin M Dougherty": "6",
      "Christine Donohue": "7",
      "David Wecht": "8",
      "Judy Olson": "2",
      "Mike George": "6",
      "Anne Covey": "9",
      "Paul P Panepinto": "0",
      "ward": 31,
      "division": 6
    },
    {
      "Candidate": "Mike George",
      "Kevin M Dougherty": "4",
      "Christine Donohue": "2",
      "David Wecht": "3",
      "Judy Olson": "6",
      "Mike George": "1",
      "Anne Covey": "5",
      "Paul P Panepinto": "0",
      "ward": 31,
      "division": 6
    },
    {
      "Candidate": "Anne Covey",
      "Kevin M Dougherty": "3",
      "Christine Donohue": "1",
      "David Wecht": "0",
      "Judy Olson": "9",
      "Mike George": "5",
      "Anne Covey": "0",
      "Paul P Panepinto": "0",
      "ward": 31,
      "division": 6
    },
    {
      "Candidate": "Paul P Panepinto",
      "Kevin M Dougherty": "1",
      "Christine Donohue": "2",
      "David Wecht": "3",
      "Judy Olson": "0",
      "Mike George": "0",
      "Anne Covey": "0",
      "Paul P Panepinto": "0",
      "ward": 31,
      "division": 6
    },
    {
      "Candidate": "Total",
      "Kevin M Dougherty": "102",
      "Christine Donohue": "79",
      "David Wecht": "79",
      "Judy Olson": "20",
      "Mike George": "11",
      "Anne Covey": "9",
      "Paul P Panepinto": "3",
      "ward": 31,
      "division": 6
    }
  ],
  [
    {
      "Candidate": "",
      "Kevin M Dougherty": "Kevin M Dougherty",
      "Christine Donohue": "Christine Donohue",
      "David Wecht": "David Wecht",
      "Judy Olson": "Judy Olson",
      "Anne Covey": "Anne Covey",
      "Mike George": "Mike George",
      "Paul P Panepinto": "Paul P Panepinto",
      "ward": 31,
      "division": 7
    },
    {
      "Candidate": "Kevin M Dougherty",
      "Kevin M Dougherty": "45",
      "Christine Donohue": "111",
      "David Wecht": "104",
      "Judy Olson": "10",
      "Anne Covey": "6",
      "Mike George": "6",
      "Paul P Panepinto": "3",
      "ward": 31,
      "division": 7
    },
    {
      "Candidate": "Christine Donohue",
      "Kevin M Dougherty": "111",
      "Christine Donohue": "5",
      "David Wecht": "115",
      "Judy Olson": "8",
      "Anne Covey": "4",
      "Mike George": "2",
      "Paul P Panepinto": "5",
      "ward": 31,
      "division": 7
    },
    {
      "Candidate": "David Wecht",
      "Kevin M Dougherty": "104",
      "Christine Donohue": "115",
      "David Wecht": "3",
      "Judy Olson": "4",
      "Anne Covey": "0",
      "Mike George": "2",
      "Paul P Panepinto": "4",
      "ward": 31,
      "division": 7
    },
    {
      "Candidate": "Judy Olson",
      "Kevin M Dougherty": "10",
      "Christine Donohue": "8",
      "David Wecht": "4",
      "Judy Olson": "1",
      "Anne Covey": "22",
      "Mike George": "17",
      "Paul P Panepinto": "3",
      "ward": 31,
      "division": 7
    },
    {
      "Candidate": "Anne Covey",
      "Kevin M Dougherty": "6",
      "Christine Donohue": "4",
      "David Wecht": "0",
      "Judy Olson": "22",
      "Anne Covey": "0",
      "Mike George": "15",
      "Paul P Panepinto": "1",
      "ward": 31,
      "division": 7
    },
    {
      "Candidate": "Mike George",
      "Kevin M Dougherty": "6",
      "Christine Donohue": "2",
      "David Wecht": "2",
      "Judy Olson": "17",
      "Anne Covey": "15",
      "Mike George": "1",
      "Paul P Panepinto": "0",
      "ward": 31,
      "division": 7
    },
    {
      "Candidate": "Paul P Panepinto",
      "Kevin M Dougherty": "3",
      "Christine Donohue": "5",
      "David Wecht": "4",
      "Judy Olson": "3",
      "Anne Covey": "1",
      "Mike George": "0",
      "Paul P Panepinto": "1",
      "ward": 31,
      "division": 7
    },
    {
      "Candidate": "Total",
      "Kevin M Dougherty": "167",
      "Christine Donohue": "133",
      "David Wecht": "120",
      "Judy Olson": "34",
      "Anne Covey": "26",
      "Mike George": "22",
      "Paul P Panepinto": "9",
      "ward": 31,
      "division": 7
    }
  ],
  [
    {
      "Candidate": "",
      "Kevin M Dougherty": "Kevin M Dougherty",
      "Christine Donohue": "Christine Donohue",
      "David Wecht": "David Wecht",
      "Judy Olson": "Judy Olson",
      "Anne Covey": "Anne Covey",
      "Mike George": "Mike George",
      "Paul P Panepinto": "Paul P Panepinto",
      "ward": 31,
      "division": 8
    },
    {
      "Candidate": "Kevin M Dougherty",
      "Kevin M Dougherty": "20",
      "Christine Donohue": "70",
      "David Wecht": "67",
      "Judy Olson": "2",
      "Anne Covey": "2",
      "Mike George": "2",
      "Paul P Panepinto": "6",
      "ward": 31,
      "division": 8
    },
    {
      "Candidate": "Christine Donohue",
      "Kevin M Dougherty": "70",
      "Christine Donohue": "8",
      "David Wecht": "68",
      "Judy Olson": "2",
      "Anne Covey": "0",
      "Mike George": "0",
      "Paul P Panepinto": "5",
      "ward": 31,
      "division": 8
    },
    {
      "Candidate": "David Wecht",
      "Kevin M Dougherty": "67",
      "Christine Donohue": "68",
      "David Wecht": "1",
      "Judy Olson": "2",
      "Anne Covey": "0",
      "Mike George": "1",
      "Paul P Panepinto": "2",
      "ward": 31,
      "division": 8
    },
    {
      "Candidate": "Judy Olson",
      "Kevin M Dougherty": "2",
      "Christine Donohue": "2",
      "David Wecht": "2",
      "Judy Olson": "1",
      "Anne Covey": "8",
      "Mike George": "7",
      "Paul P Panepinto": "0",
      "ward": 31,
      "division": 8
    },
    {
      "Candidate": "Anne Covey",
      "Kevin M Dougherty": "2",
      "Christine Donohue": "0",
      "David Wecht": "0",
      "Judy Olson": "8",
      "Anne Covey": "0",
      "Mike George": "6",
      "Paul P Panepinto": "1",
      "ward": 31,
      "division": 8
    },
    {
      "Candidate": "Mike George",
      "Kevin M Dougherty": "2",
      "Christine Donohue": "0",
      "David Wecht": "1",
      "Judy Olson": "7",
      "Anne Covey": "6",
      "Mike George": "0",
      "Paul P Panepinto": "0",
      "ward": 31,
      "division": 8
    },
    {
      "Candidate": "Paul P Panepinto",
      "Kevin M Dougherty": "6",
      "Christine Donohue": "5",
      "David Wecht": "2",
      "Judy Olson": "0",
      "Anne Covey": "1",
      "Mike George": "0",
      "Paul P Panepinto": "0",
      "ward": 31,
      "division": 8
    },
    {
      "Candidate": "Total",
      "Kevin M Dougherty": "96",
      "Christine Donohue": "82",
      "David Wecht": "72",
      "Judy Olson": "12",
      "Anne Covey": "9",
      "Mike George": "8",
      "Paul P Panepinto": "7",
      "ward": 31,
      "division": 8
    }
  ],
  [
    {
      "Candidate": "",
      "Kevin M Dougherty": "Kevin M Dougherty",
      "David Wecht": "David Wecht",
      "Christine Donohue": "Christine Donohue",
      "Anne Covey": "Anne Covey",
      "Judy Olson": "Judy Olson",
      "Mike George": "Mike George",
      "Paul P Panepinto": "Paul P Panepinto",
      "ward": 31,
      "division": 9
    },
    {
      "Candidate": "Kevin M Dougherty",
      "Kevin M Dougherty": "18",
      "David Wecht": "49",
      "Christine Donohue": "47",
      "Anne Covey": "1",
      "Judy Olson": "0",
      "Mike George": "0",
      "Paul P Panepinto": "0",
      "ward": 31,
      "division": 9
    },
    {
      "Candidate": "David Wecht",
      "Kevin M Dougherty": "49",
      "David Wecht": "2",
      "Christine Donohue": "50",
      "Anne Covey": "1",
      "Judy Olson": "1",
      "Mike George": "0",
      "Paul P Panepinto": "3",
      "ward": 31,
      "division": 9
    },
    {
      "Candidate": "Christine Donohue",
      "Kevin M Dougherty": "47",
      "David Wecht": "50",
      "Christine Donohue": "2",
      "Anne Covey": "0",
      "Judy Olson": "1",
      "Mike George": "0",
      "Paul P Panepinto": "3",
      "ward": 31,
      "division": 9
    },
    {
      "Candidate": "Anne Covey",
      "Kevin M Dougherty": "1",
      "David Wecht": "1",
      "Christine Donohue": "0",
      "Anne Covey": "0",
      "Judy Olson": "5",
      "Mike George": "5",
      "Paul P Panepinto": "0",
      "ward": 31,
      "division": 9
    },
    {
      "Candidate": "Judy Olson",
      "Kevin M Dougherty": "0",
      "David Wecht": "1",
      "Christine Donohue": "1",
      "Anne Covey": "5",
      "Judy Olson": "0",
      "Mike George": "5",
      "Paul P Panepinto": "0",
      "ward": 31,
      "division": 9
    },
    {
      "Candidate": "Mike George",
      "Kevin M Dougherty": "0",
      "David Wecht": "0",
      "Christine Donohue": "0",
      "Anne Covey": "5",
      "Judy Olson": "5",
      "Mike George": "1",
      "Paul P Panepinto": "0",
      "ward": 31,
      "division": 9
    },
    {
      "Candidate": "Paul P Panepinto",
      "Kevin M Dougherty": "0",
      "David Wecht": "3",
      "Christine Donohue": "3",
      "Anne Covey": "0",
      "Judy Olson": "0",
      "Mike George": "0",
      "Paul P Panepinto": "0",
      "ward": 31,
      "division": 9
    },
    {
      "Candidate": "Total",
      "Kevin M Dougherty": "68",
      "David Wecht": "55",
      "Christine Donohue": "53",
      "Anne Covey": "6",
      "Judy Olson": "6",
      "Mike George": "6",
      "Paul P Panepinto": "3",
      "ward": 31,
      "division": 9
    }
  ],
  [
    {
      "Candidate": "",
      "Kevin M Dougherty": "Kevin M Dougherty",
      "Christine Donohue": "Christine Donohue",
      "David Wecht": "David Wecht",
      "Judy Olson": "Judy Olson",
      "Anne Covey": "Anne Covey",
      "Mike George": "Mike George",
      "Paul P Panepinto": "Paul P Panepinto",
      "ward": 31,
      "division": 10
    },
    {
      "Candidate": "Kevin M Dougherty",
      "Kevin M Dougherty": "13",
      "Christine Donohue": "32",
      "David Wecht": "32",
      "Judy Olson": "0",
      "Anne Covey": "2",
      "Mike George": "1",
      "Paul P Panepinto": "0",
      "ward": 31,
      "division": 10
    },
    {
      "Candidate": "Christine Donohue",
      "Kevin M Dougherty": "32",
      "Christine Donohue": "6",
      "David Wecht": "38",
      "Judy Olson": "5",
      "Anne Covey": "1",
      "Mike George": "0",
      "Paul P Panepinto": "1",
      "ward": 31,
      "division": 10
    },
    {
      "Candidate": "David Wecht",
      "Kevin M Dougherty": "32",
      "Christine Donohue": "38",
      "David Wecht": "3",
      "Judy Olson": "5",
      "Anne Covey": "1",
      "Mike George": "0",
      "Paul P Panepinto": "2",
      "ward": 31,
      "division": 10
    },
    {
      "Candidate": "Judy Olson",
      "Kevin M Dougherty": "0",
      "Christine Donohue": "5",
      "David Wecht": "5",
      "Judy Olson": "0",
      "Anne Covey": "4",
      "Mike George": "4",
      "Paul P Panepinto": "0",
      "ward": 31,
      "division": 10
    },
    {
      "Candidate": "Anne Covey",
      "Kevin M Dougherty": "2",
      "Christine Donohue": "1",
      "David Wecht": "1",
      "Judy Olson": "4",
      "Anne Covey": "0",
      "Mike George": "5",
      "Paul P Panepinto": "1",
      "ward": 31,
      "division": 10
    },
    {
      "Candidate": "Mike George",
      "Kevin M Dougherty": "1",
      "Christine Donohue": "0",
      "David Wecht": "0",
      "Judy Olson": "4",
      "Anne Covey": "5",
      "Mike George": "0",
      "Paul P Panepinto": "1",
      "ward": 31,
      "division": 10
    },
    {
      "Candidate": "Paul P Panepinto",
      "Kevin M Dougherty": "0",
      "Christine Donohue": "1",
      "David Wecht": "2",
      "Judy Olson": "0",
      "Anne Covey": "1",
      "Mike George": "1",
      "Paul P Panepinto": "1",
      "ward": 31,
      "division": 10
    },
    {
      "Candidate": "Total",
      "Kevin M Dougherty": "47",
      "Christine Donohue": "45",
      "David Wecht": "43",
      "Judy Olson": "9",
      "Anne Covey": "7",
      "Mike George": "6",
      "Paul P Panepinto": "4",
      "ward": 31,
      "division": 10
    }
  ],
  [
    {
      "Candidate": "",
      "Kevin M Dougherty": "Kevin M Dougherty",
      "Christine Donohue": "Christine Donohue",
      "David Wecht": "David Wecht",
      "Judy Olson": "Judy Olson",
      "Mike George": "Mike George",
      "Anne Covey": "Anne Covey",
      "Paul P Panepinto": "Paul P Panepinto",
      "ward": 31,
      "division": 11
    },
    {
      "Candidate": "Kevin M Dougherty",
      "Kevin M Dougherty": "23",
      "Christine Donohue": "83",
      "David Wecht": "77",
      "Judy Olson": "6",
      "Mike George": "4",
      "Anne Covey": "1",
      "Paul P Panepinto": "1",
      "ward": 31,
      "division": 11
    },
    {
      "Candidate": "Christine Donohue",
      "Kevin M Dougherty": "83",
      "Christine Donohue": "2",
      "David Wecht": "83",
      "Judy Olson": "9",
      "Mike George": "0",
      "Anne Covey": "1",
      "Paul P Panepinto": "4",
      "ward": 31,
      "division": 11
    },
    {
      "Candidate": "David Wecht",
      "Kevin M Dougherty": "77",
      "Christine Donohue": "83",
      "David Wecht": "6",
      "Judy Olson": "5",
      "Mike George": "2",
      "Anne Covey": "1",
      "Paul P Panepinto": "2",
      "ward": 31,
      "division": 11
    },
    {
      "Candidate": "Judy Olson",
      "Kevin M Dougherty": "6",
      "Christine Donohue": "9",
      "David Wecht": "5",
      "Judy Olson": "1",
      "Mike George": "4",
      "Anne Covey": "4",
      "Paul P Panepinto": "0",
      "ward": 31,
      "division": 11
    },
    {
      "Candidate": "Mike George",
      "Kevin M Dougherty": "4",
      "Christine Donohue": "0",
      "David Wecht": "2",
      "Judy Olson": "4",
      "Mike George": "0",
      "Anne Covey": "3",
      "Paul P Panepinto": "0",
      "ward": 31,
      "division": 11
    },
    {
      "Candidate": "Anne Covey",
      "Kevin M Dougherty": "1",
      "Christine Donohue": "1",
      "David Wecht": "1",
      "Judy Olson": "4",
      "Mike George": "3",
      "Anne Covey": "0",
      "Paul P Panepinto": "0",
      "ward": 31,
      "division": 11
    },
    {
      "Candidate": "Paul P Panepinto",
      "Kevin M Dougherty": "1",
      "Christine Donohue": "4",
      "David Wecht": "2",
      "Judy Olson": "0",
      "Mike George": "0",
      "Anne Covey": "0",
      "Paul P Panepinto": "0",
      "ward": 31,
      "division": 11
    },
    {
      "Candidate": "Total",
      "Kevin M Dougherty": "114",
      "Christine Donohue": "96",
      "David Wecht": "93",
      "Judy Olson": "16",
      "Mike George": "7",
      "Anne Covey": "6",
      "Paul P Panepinto": "4",
      "ward": 31,
      "division": 11
    }
  ],
  [
    {
      "Candidate": "",
      "Kevin M Dougherty": "Kevin M Dougherty",
      "Christine Donohue": "Christine Donohue",
      "David Wecht": "David Wecht",
      "Judy Olson": "Judy Olson",
      "Anne Covey": "Anne Covey",
      "Mike George": "Mike George",
      "Paul P Panepinto": "Paul P Panepinto",
      "ward": 31,
      "division": 12
    },
    {
      "Candidate": "Kevin M Dougherty",
      "Kevin M Dougherty": "9",
      "Christine Donohue": "56",
      "David Wecht": "53",
      "Judy Olson": "5",
      "Anne Covey": "4",
      "Mike George": "0",
      "Paul P Panepinto": "1",
      "ward": 31,
      "division": 12
    },
    {
      "Candidate": "Christine Donohue",
      "Kevin M Dougherty": "56",
      "Christine Donohue": "3",
      "David Wecht": "58",
      "Judy Olson": "4",
      "Anne Covey": "1",
      "Mike George": "0",
      "Paul P Panepinto": "0",
      "ward": 31,
      "division": 12
    },
    {
      "Candidate": "David Wecht",
      "Kevin M Dougherty": "53",
      "Christine Donohue": "58",
      "David Wecht": "1",
      "Judy Olson": "3",
      "Anne Covey": "0",
      "Mike George": "0",
      "Paul P Panepinto": "0",
      "ward": 31,
      "division": 12
    },
    {
      "Candidate": "Judy Olson",
      "Kevin M Dougherty": "5",
      "Christine Donohue": "4",
      "David Wecht": "3",
      "Judy Olson": "0",
      "Anne Covey": "7",
      "Mike George": "5",
      "Paul P Panepinto": "0",
      "ward": 31,
      "division": 12
    },
    {
      "Candidate": "Anne Covey",
      "Kevin M Dougherty": "4",
      "Christine Donohue": "1",
      "David Wecht": "0",
      "Judy Olson": "7",
      "Anne Covey": "0",
      "Mike George": "4",
      "Paul P Panepinto": "0",
      "ward": 31,
      "division": 12
    },
    {
      "Candidate": "Mike George",
      "Kevin M Dougherty": "0",
      "Christine Donohue": "0",
      "David Wecht": "0",
      "Judy Olson": "5",
      "Anne Covey": "4",
      "Mike George": "0",
      "Paul P Panepinto": "0",
      "ward": 31,
      "division": 12
    },
    {
      "Candidate": "Paul P Panepinto",
      "Kevin M Dougherty": "1",
      "Christine Donohue": "0",
      "David Wecht": "0",
      "Judy Olson": "0",
      "Anne Covey": "0",
      "Mike George": "0",
      "Paul P Panepinto": "0",
      "ward": 31,
      "division": 12
    },
    {
      "Candidate": "Total",
      "Kevin M Dougherty": "70",
      "Christine Donohue": "64",
      "David Wecht": "59",
      "Judy Olson": "13",
      "Anne Covey": "8",
      "Mike George": "5",
      "Paul P Panepinto": "1",
      "ward": 31,
      "division": 12
    }
  ],
  [
    {
      "Candidate": "",
      "Kevin M Dougherty": "Kevin M Dougherty",
      "Christine Donohue": "Christine Donohue",
      "David Wecht": "David Wecht",
      "Judy Olson": "Judy Olson",
      "Anne Covey": "Anne Covey",
      "Mike George": "Mike George",
      "Paul P Panepinto": "Paul P Panepinto",
      "ward": 31,
      "division": 13
    },
    {
      "Candidate": "Kevin M Dougherty",
      "Kevin M Dougherty": "31",
      "Christine Donohue": "100",
      "David Wecht": "93",
      "Judy Olson": "2",
      "Anne Covey": "2",
      "Mike George": "0",
      "Paul P Panepinto": "4",
      "ward": 31,
      "division": 13
    },
    {
      "Candidate": "Christine Donohue",
      "Kevin M Dougherty": "100",
      "Christine Donohue": "2",
      "David Wecht": "95",
      "Judy Olson": "7",
      "Anne Covey": "4",
      "Mike George": "1",
      "Paul P Panepinto": "3",
      "ward": 31,
      "division": 13
    },
    {
      "Candidate": "David Wecht",
      "Kevin M Dougherty": "93",
      "Christine Donohue": "95",
      "David Wecht": "2",
      "Judy Olson": "7",
      "Anne Covey": "0",
      "Mike George": "0",
      "Paul P Panepinto": "4",
      "ward": 31,
      "division": 13
    },
    {
      "Candidate": "Judy Olson",
      "Kevin M Dougherty": "2",
      "Christine Donohue": "7",
      "David Wecht": "7",
      "Judy Olson": "1",
      "Anne Covey": "18",
      "Mike George": "14",
      "Paul P Panepinto": "1",
      "ward": 31,
      "division": 13
    },
    {
      "Candidate": "Anne Covey",
      "Kevin M Dougherty": "2",
      "Christine Donohue": "4",
      "David Wecht": "0",
      "Judy Olson": "18",
      "Anne Covey": "0",
      "Mike George": "15",
      "Paul P Panepinto": "1",
      "ward": 31,
      "division": 13
    },
    {
      "Candidate": "Mike George",
      "Kevin M Dougherty": "0",
      "Christine Donohue": "1",
      "David Wecht": "0",
      "Judy Olson": "14",
      "Anne Covey": "15",
      "Mike George": "0",
      "Paul P Panepinto": "1",
      "ward": 31,
      "division": 13
    },
    {
      "Candidate": "Paul P Panepinto",
      "Kevin M Dougherty": "4",
      "Christine Donohue": "3",
      "David Wecht": "4",
      "Judy Olson": "1",
      "Anne Covey": "1",
      "Mike George": "1",
      "Paul P Panepinto": "0",
      "ward": 31,
      "division": 13
    },
    {
      "Candidate": "Total",
      "Kevin M Dougherty": "137",
      "Christine Donohue": "111",
      "David Wecht": "103",
      "Judy Olson": "27",
      "Anne Covey": "21",
      "Mike George": "16",
      "Paul P Panepinto": "8",
      "ward": 31,
      "division": 13
    }
  ],
  [
    {
      "Candidate": "",
      "Kevin M Dougherty": "Kevin M Dougherty",
      "Christine Donohue": "Christine Donohue",
      "David Wecht": "David Wecht",
      "Anne Covey": "Anne Covey",
      "Judy Olson": "Judy Olson",
      "Mike George": "Mike George",
      "Paul P Panepinto": "Paul P Panepinto",
      "ward": 31,
      "division": 14
    },
    {
      "Candidate": "Kevin M Dougherty",
      "Kevin M Dougherty": "31",
      "Christine Donohue": "97",
      "David Wecht": "95",
      "Anne Covey": "6",
      "Judy Olson": "4",
      "Mike George": "1",
      "Paul P Panepinto": "3",
      "ward": 31,
      "division": 14
    },
    {
      "Candidate": "Christine Donohue",
      "Kevin M Dougherty": "97",
      "Christine Donohue": "5",
      "David Wecht": "96",
      "Anne Covey": "4",
      "Judy Olson": "8",
      "Mike George": "2",
      "Paul P Panepinto": "3",
      "ward": 31,
      "division": 14
    },
    {
      "Candidate": "David Wecht",
      "Kevin M Dougherty": "95",
      "Christine Donohue": "96",
      "David Wecht": "1",
      "Anne Covey": "3",
      "Judy Olson": "5",
      "Mike George": "2",
      "Paul P Panepinto": "2",
      "ward": 31,
      "division": 14
    },
    {
      "Candidate": "Anne Covey",
      "Kevin M Dougherty": "6",
      "Christine Donohue": "4",
      "David Wecht": "3",
      "Anne Covey": "2",
      "Judy Olson": "18",
      "Mike George": "18",
      "Paul P Panepinto": "2",
      "ward": 31,
      "division": 14
    },
    {
      "Candidate": "Judy Olson",
      "Kevin M Dougherty": "4",
      "Christine Donohue": "8",
      "David Wecht": "5",
      "Anne Covey": "18",
      "Judy Olson": "1",
      "Mike George": "17",
      "Paul P Panepinto": "1",
      "ward": 31,
      "division": 14
    },
    {
      "Candidate": "Mike George",
      "Kevin M Dougherty": "1",
      "Christine Donohue": "2",
      "David Wecht": "2",
      "Anne Covey": "18",
      "Judy Olson": "17",
      "Mike George": "1",
      "Paul P Panepinto": "1",
      "ward": 31,
      "division": 14
    },
    {
      "Candidate": "Paul P Panepinto",
      "Kevin M Dougherty": "3",
      "Christine Donohue": "3",
      "David Wecht": "2",
      "Anne Covey": "2",
      "Judy Olson": "1",
      "Mike George": "1",
      "Paul P Panepinto": "0",
      "ward": 31,
      "division": 14
    },
    {
      "Candidate": "Total",
      "Kevin M Dougherty": "138",
      "Christine Donohue": "113",
      "David Wecht": "105",
      "Anne Covey": "30",
      "Judy Olson": "28",
      "Mike George": "22",
      "Paul P Panepinto": "6",
      "ward": 31,
      "division": 14
    }
  ],
  [
    {
      "Candidate": "",
      "Kevin M Dougherty": "Kevin M Dougherty",
      "Christine Donohue": "Christine Donohue",
      "David Wecht": "David Wecht",
      "Judy Olson": "Judy Olson",
      "Anne Covey": "Anne Covey",
      "Mike George": "Mike George",
      "Paul P Panepinto": "Paul P Panepinto",
      "ward": 31,
      "division": 15
    },
    {
      "Candidate": "Kevin M Dougherty",
      "Kevin M Dougherty": "41",
      "Christine Donohue": "82",
      "David Wecht": "74",
      "Judy Olson": "8",
      "Anne Covey": "4",
      "Mike George": "1",
      "Paul P Panepinto": "1",
      "ward": 31,
      "division": 15
    },
    {
      "Candidate": "Christine Donohue",
      "Kevin M Dougherty": "82",
      "Christine Donohue": "4",
      "David Wecht": "82",
      "Judy Olson": "7",
      "Anne Covey": "2",
      "Mike George": "1",
      "Paul P Panepinto": "3",
      "ward": 31,
      "division": 15
    },
    {
      "Candidate": "David Wecht",
      "Kevin M Dougherty": "74",
      "Christine Donohue": "82",
      "David Wecht": "1",
      "Judy Olson": "2",
      "Anne Covey": "0",
      "Mike George": "1",
      "Paul P Panepinto": "2",
      "ward": 31,
      "division": 15
    },
    {
      "Candidate": "Judy Olson",
      "Kevin M Dougherty": "8",
      "Christine Donohue": "7",
      "David Wecht": "2",
      "Judy Olson": "0",
      "Anne Covey": "18",
      "Mike George": "15",
      "Paul P Panepinto": "1",
      "ward": 31,
      "division": 15
    },
    {
      "Candidate": "Anne Covey",
      "Kevin M Dougherty": "4",
      "Christine Donohue": "2",
      "David Wecht": "0",
      "Judy Olson": "18",
      "Anne Covey": "3",
      "Mike George": "14",
      "Paul P Panepinto": "2",
      "ward": 31,
      "division": 15
    },
    {
      "Candidate": "Mike George",
      "Kevin M Dougherty": "1",
      "Christine Donohue": "1",
      "David Wecht": "1",
      "Judy Olson": "15",
      "Anne Covey": "14",
      "Mike George": "2",
      "Paul P Panepinto": "1",
      "ward": 31,
      "division": 15
    },
    {
      "Candidate": "Paul P Panepinto",
      "Kevin M Dougherty": "1",
      "Christine Donohue": "3",
      "David Wecht": "2",
      "Judy Olson": "1",
      "Anne Covey": "2",
      "Mike George": "1",
      "Paul P Panepinto": "0",
      "ward": 31,
      "division": 15
    },
    {
      "Candidate": "Total",
      "Kevin M Dougherty": "130",
      "Christine Donohue": "97",
      "David Wecht": "84",
      "Judy Olson": "26",
      "Anne Covey": "23",
      "Mike George": "19",
      "Paul P Panepinto": "5",
      "ward": 31,
      "division": 15
    }
  ],
  [
    {
      "Candidate": "",
      "Kevin M Dougherty": "Kevin M Dougherty",
      "Christine Donohue": "Christine Donohue",
      "David Wecht": "David Wecht",
      "Judy Olson": "Judy Olson",
      "Anne Covey": "Anne Covey",
      "Mike George": "Mike George",
      "Paul P Panepinto": "Paul P Panepinto",
      "ward": 31,
      "division": 16
    },
    {
      "Candidate": "Kevin M Dougherty",
      "Kevin M Dougherty": "52",
      "Christine Donohue": "105",
      "David Wecht": "96",
      "Judy Olson": "11",
      "Anne Covey": "8",
      "Mike George": "3",
      "Paul P Panepinto": "2",
      "ward": 31,
      "division": 16
    },
    {
      "Candidate": "Christine Donohue",
      "Kevin M Dougherty": "105",
      "Christine Donohue": "3",
      "David Wecht": "101",
      "Judy Olson": "8",
      "Anne Covey": "1",
      "Mike George": "2",
      "Paul P Panepinto": "3",
      "ward": 31,
      "division": 16
    },
    {
      "Candidate": "David Wecht",
      "Kevin M Dougherty": "96",
      "Christine Donohue": "101",
      "David Wecht": "2",
      "Judy Olson": "7",
      "Anne Covey": "1",
      "Mike George": "0",
      "Paul P Panepinto": "3",
      "ward": 31,
      "division": 16
    },
    {
      "Candidate": "Judy Olson",
      "Kevin M Dougherty": "11",
      "Christine Donohue": "8",
      "David Wecht": "7",
      "Judy Olson": "6",
      "Anne Covey": "24",
      "Mike George": "17",
      "Paul P Panepinto": "2",
      "ward": 31,
      "division": 16
    },
    {
      "Candidate": "Anne Covey",
      "Kevin M Dougherty": "8",
      "Christine Donohue": "1",
      "David Wecht": "1",
      "Judy Olson": "24",
      "Anne Covey": "0",
      "Mike George": "13",
      "Paul P Panepinto": "0",
      "ward": 31,
      "division": 16
    },
    {
      "Candidate": "Mike George",
      "Kevin M Dougherty": "3",
      "Christine Donohue": "2",
      "David Wecht": "0",
      "Judy Olson": "17",
      "Anne Covey": "13",
      "Mike George": "0",
      "Paul P Panepinto": "2",
      "ward": 31,
      "division": 16
    },
    {
      "Candidate": "Paul P Panepinto",
      "Kevin M Dougherty": "2",
      "Christine Donohue": "3",
      "David Wecht": "3",
      "Judy Olson": "2",
      "Anne Covey": "0",
      "Mike George": "2",
      "Paul P Panepinto": "0",
      "ward": 31,
      "division": 16
    },
    {
      "Candidate": "Total",
      "Kevin M Dougherty": "171",
      "Christine Donohue": "119",
      "David Wecht": "109",
      "Judy Olson": "42",
      "Anne Covey": "25",
      "Mike George": "19",
      "Paul P Panepinto": "6",
      "ward": 31,
      "division": 16
    }
  ],
  [
    {
      "Candidate": "",
      "Kevin M Dougherty": "Kevin M Dougherty",
      "Christine Donohue": "Christine Donohue",
      "David Wecht": "David Wecht",
      "Judy Olson": "Judy Olson",
      "Anne Covey": "Anne Covey",
      "Mike George": "Mike George",
      "Paul P Panepinto": "Paul P Panepinto",
      "ward": 31,
      "division": 17
    },
    {
      "Candidate": "Kevin M Dougherty",
      "Kevin M Dougherty": "24",
      "Christine Donohue": "71",
      "David Wecht": "66",
      "Judy Olson": "7",
      "Anne Covey": "4",
      "Mike George": "3",
      "Paul P Panepinto": "2",
      "ward": 31,
      "division": 17
    },
    {
      "Candidate": "Christine Donohue",
      "Kevin M Dougherty": "71",
      "Christine Donohue": "3",
      "David Wecht": "70",
      "Judy Olson": "5",
      "Anne Covey": "1",
      "Mike George": "1",
      "Paul P Panepinto": "3",
      "ward": 31,
      "division": 17
    },
    {
      "Candidate": "David Wecht",
      "Kevin M Dougherty": "66",
      "Christine Donohue": "70",
      "David Wecht": "2",
      "Judy Olson": "4",
      "Anne Covey": "1",
      "Mike George": "2",
      "Paul P Panepinto": "1",
      "ward": 31,
      "division": 17
    },
    {
      "Candidate": "Judy Olson",
      "Kevin M Dougherty": "7",
      "Christine Donohue": "5",
      "David Wecht": "4",
      "Judy Olson": "4",
      "Anne Covey": "18",
      "Mike George": "17",
      "Paul P Panepinto": "1",
      "ward": 31,
      "division": 17
    },
    {
      "Candidate": "Anne Covey",
      "Kevin M Dougherty": "4",
      "Christine Donohue": "1",
      "David Wecht": "1",
      "Judy Olson": "18",
      "Anne Covey": "0",
      "Mike George": "12",
      "Paul P Panepinto": "1",
      "ward": 31,
      "division": 17
    },
    {
      "Candidate": "Mike George",
      "Kevin M Dougherty": "3",
      "Christine Donohue": "1",
      "David Wecht": "2",
      "Judy Olson": "17",
      "Anne Covey": "12",
      "Mike George": "1",
      "Paul P Panepinto": "0",
      "ward": 31,
      "division": 17
    },
    {
      "Candidate": "Paul P Panepinto",
      "Kevin M Dougherty": "2",
      "Christine Donohue": "3",
      "David Wecht": "1",
      "Judy Olson": "1",
      "Anne Covey": "1",
      "Mike George": "0",
      "Paul P Panepinto": "0",
      "ward": 31,
      "division": 17
    },
    {
      "Candidate": "Total",
      "Kevin M Dougherty": "102",
      "Christine Donohue": "80",
      "David Wecht": "74",
      "Judy Olson": "31",
      "Anne Covey": "19",
      "Mike George": "19",
      "Paul P Panepinto": "4",
      "ward": 31,
      "division": 17
    }
  ],
  [
    {
      "Candidate": "",
      "Kevin M Dougherty": "Kevin M Dougherty",
      "Christine Donohue": "Christine Donohue",
      "David Wecht": "David Wecht",
      "Anne Covey": "Anne Covey",
      "Judy Olson": "Judy Olson",
      "Mike George": "Mike George",
      "Paul P Panepinto": "Paul P Panepinto",
      "ward": 31,
      "division": 18
    },
    {
      "Candidate": "Kevin M Dougherty",
      "Kevin M Dougherty": "33",
      "Christine Donohue": "62",
      "David Wecht": "64",
      "Anne Covey": "5",
      "Judy Olson": "0",
      "Mike George": "1",
      "Paul P Panepinto": "1",
      "ward": 31,
      "division": 18
    },
    {
      "Candidate": "Christine Donohue",
      "Kevin M Dougherty": "62",
      "Christine Donohue": "4",
      "David Wecht": "63",
      "Anne Covey": "2",
      "Judy Olson": "2",
      "Mike George": "0",
      "Paul P Panepinto": "2",
      "ward": 31,
      "division": 18
    },
    {
      "Candidate": "David Wecht",
      "Kevin M Dougherty": "64",
      "Christine Donohue": "63",
      "David Wecht": "3",
      "Anne Covey": "2",
      "Judy Olson": "1",
      "Mike George": "0",
      "Paul P Panepinto": "3",
      "ward": 31,
      "division": 18
    },
    {
      "Candidate": "Anne Covey",
      "Kevin M Dougherty": "5",
      "Christine Donohue": "2",
      "David Wecht": "2",
      "Anne Covey": "1",
      "Judy Olson": "8",
      "Mike George": "8",
      "Paul P Panepinto": "0",
      "ward": 31,
      "division": 18
    },
    {
      "Candidate": "Judy Olson",
      "Kevin M Dougherty": "0",
      "Christine Donohue": "2",
      "David Wecht": "1",
      "Anne Covey": "8",
      "Judy Olson": "1",
      "Mike George": "7",
      "Paul P Panepinto": "0",
      "ward": 31,
      "division": 18
    },
    {
      "Candidate": "Mike George",
      "Kevin M Dougherty": "1",
      "Christine Donohue": "0",
      "David Wecht": "0",
      "Anne Covey": "8",
      "Judy Olson": "7",
      "Mike George": "1",
      "Paul P Panepinto": "0",
      "ward": 31,
      "division": 18
    },
    {
      "Candidate": "Paul P Panepinto",
      "Kevin M Dougherty": "1",
      "Christine Donohue": "2",
      "David Wecht": "3",
      "Anne Covey": "0",
      "Judy Olson": "0",
      "Mike George": "0",
      "Paul P Panepinto": "0",
      "ward": 31,
      "division": 18
    },
    {
      "Candidate": "Total",
      "Kevin M Dougherty": "102",
      "Christine Donohue": "71",
      "David Wecht": "71",
      "Anne Covey": "14",
      "Judy Olson": "10",
      "Mike George": "9",
      "Paul P Panepinto": "3",
      "ward": 31,
      "division": 18
    }
  ],
  [
    {
      "Candidate": "",
      "Kevin M Dougherty": "Kevin M Dougherty",
      "Christine Donohue": "Christine Donohue",
      "David Wecht": "David Wecht",
      "Judy Olson": "Judy Olson",
      "Anne Covey": "Anne Covey",
      "Paul P Panepinto": "Paul P Panepinto",
      "Mike George": "Mike George",
      "ward": 31,
      "division": 19
    },
    {
      "Candidate": "Kevin M Dougherty",
      "Kevin M Dougherty": "50",
      "Christine Donohue": "70",
      "David Wecht": "62",
      "Judy Olson": "9",
      "Anne Covey": "6",
      "Paul P Panepinto": "5",
      "Mike George": "3",
      "ward": 31,
      "division": 19
    },
    {
      "Candidate": "Christine Donohue",
      "Kevin M Dougherty": "70",
      "Christine Donohue": "3",
      "David Wecht": "64",
      "Judy Olson": "5",
      "Anne Covey": "1",
      "Paul P Panepinto": "4",
      "Mike George": "0",
      "ward": 31,
      "division": 19
    },
    {
      "Candidate": "David Wecht",
      "Kevin M Dougherty": "62",
      "Christine Donohue": "64",
      "David Wecht": "2",
      "Judy Olson": "2",
      "Anne Covey": "0",
      "Paul P Panepinto": "0",
      "Mike George": "0",
      "ward": 31,
      "division": 19
    },
    {
      "Candidate": "Judy Olson",
      "Kevin M Dougherty": "9",
      "Christine Donohue": "5",
      "David Wecht": "2",
      "Judy Olson": "0",
      "Anne Covey": "6",
      "Paul P Panepinto": "1",
      "Mike George": "3",
      "ward": 31,
      "division": 19
    },
    {
      "Candidate": "Anne Covey",
      "Kevin M Dougherty": "6",
      "Christine Donohue": "1",
      "David Wecht": "0",
      "Judy Olson": "6",
      "Anne Covey": "0",
      "Paul P Panepinto": "0",
      "Mike George": "1",
      "ward": 31,
      "division": 19
    },
    {
      "Candidate": "Paul P Panepinto",
      "Kevin M Dougherty": "5",
      "Christine Donohue": "4",
      "David Wecht": "0",
      "Judy Olson": "1",
      "Anne Covey": "0",
      "Paul P Panepinto": "0",
      "Mike George": "0",
      "ward": 31,
      "division": 19
    },
    {
      "Candidate": "Mike George",
      "Kevin M Dougherty": "3",
      "Christine Donohue": "0",
      "David Wecht": "0",
      "Judy Olson": "3",
      "Anne Covey": "1",
      "Paul P Panepinto": "0",
      "Mike George": "0",
      "ward": 31,
      "division": 19
    },
    {
      "Candidate": "Total",
      "Kevin M Dougherty": "132",
      "Christine Donohue": "78",
      "David Wecht": "68",
      "Judy Olson": "13",
      "Anne Covey": "7",
      "Paul P Panepinto": "6",
      "Mike George": "4",
      "ward": 31,
      "division": 19
    }
  ]
]
