[
  [
    {
      "Candidate": "",
      "Michael H O Brien": "Michael H O Brien",
      "Write In": "Write In",
      "ward": 25,
      "division": "All"
    },
    {
      "Candidate": "Michael H O Brien",
      "Michael H O Brien": "786",
      "Write In": "0",
      "ward": 25,
      "division": "All"
    },
    {
      "Candidate": "Write In",
      "Michael H O Brien": "",
      "Write In": "2",
      "ward": 25,
      "division": "All"
    },
    {
      "Candidate": "Total",
      "Michael H O Brien": "786",
      "Write In": "2",
      "ward": 25,
      "division": "All"
    }
  ],
  [
    {
      "Candidate": "",
      "Michael H O Brien": "Michael H O Brien",
      "ward": 25,
      "division": 9
    },
    {
      "Candidate": "Michael H O Brien",
      "Michael H O Brien": "76",
      "ward": 25,
      "division": 9
    },
    {
      "Candidate": "Total",
      "Michael H O Brien": "76",
      "ward": 25,
      "division": 9
    }
  ],
  [
    {
      "Candidate": "",
      "Michael H O Brien": "Michael H O Brien",
      "ward": 25,
      "division": 13
    },
    {
      "Candidate": "Michael H O Brien",
      "Michael H O Brien": "92",
      "ward": 25,
      "division": 13
    },
    {
      "Candidate": "Total",
      "Michael H O Brien": "92",
      "ward": 25,
      "division": 13
    }
  ],
  [
    {
      "Candidate": "",
      "Michael H O Brien": "Michael H O Brien",
      "ward": 25,
      "division": 14
    },
    {
      "Candidate": "Michael H O Brien",
      "Michael H O Brien": "54",
      "ward": 25,
      "division": 14
    },
    {
      "Candidate": "Total",
      "Michael H O Brien": "54",
      "ward": 25,
      "division": 14
    }
  ],
  [
    {
      "Candidate": "",
      "Michael H O Brien": "Michael H O Brien",
      "ward": 25,
      "division": 15
    },
    {
      "Candidate": "Michael H O Brien",
      "Michael H O Brien": "64",
      "ward": 25,
      "division": 15
    },
    {
      "Candidate": "Total",
      "Michael H O Brien": "64",
      "ward": 25,
      "division": 15
    }
  ],
  [
    {
      "Candidate": "",
      "Michael H O Brien": "Michael H O Brien",
      "Write In": "Write In",
      "ward": 25,
      "division": 16
    },
    {
      "Candidate": "Michael H O Brien",
      "Michael H O Brien": "59",
      "Write In": "0",
      "ward": 25,
      "division": 16
    },
    {
      "Candidate": "Write In",
      "Michael H O Brien": "",
      "Write In": "1",
      "ward": 25,
      "division": 16
    },
    {
      "Candidate": "Total",
      "Michael H O Brien": "59",
      "Write In": "1",
      "ward": 25,
      "division": 16
    }
  ],
  [
    {
      "Candidate": "",
      "Michael H O Brien": "Michael H O Brien",
      "ward": 25,
      "division": 17
    },
    {
      "Candidate": "Michael H O Brien",
      "Michael H O Brien": "60",
      "ward": 25,
      "division": 17
    },
    {
      "Candidate": "Total",
      "Michael H O Brien": "60",
      "ward": 25,
      "division": 17
    }
  ],
  [
    {
      "Candidate": "",
      "Michael H O Brien": "Michael H O Brien",
      "ward": 25,
      "division": 18
    },
    {
      "Candidate": "Michael H O Brien",
      "Michael H O Brien": "89",
      "ward": 25,
      "division": 18
    },
    {
      "Candidate": "Total",
      "Michael H O Brien": "89",
      "ward": 25,
      "division": 18
    }
  ],
  [
    {
      "Candidate": "",
      "Michael H O Brien": "Michael H O Brien",
      "ward": 25,
      "division": 19
    },
    {
      "Candidate": "Michael H O Brien",
      "Michael H O Brien": "76",
      "ward": 25,
      "division": 19
    },
    {
      "Candidate": "Total",
      "Michael H O Brien": "76",
      "ward": 25,
      "division": 19
    }
  ],
  [
    {
      "Candidate": "",
      "Michael H O Brien": "Michael H O Brien",
      "ward": 25,
      "division": 20
    },
    {
      "Candidate": "Michael H O Brien",
      "Michael H O Brien": "59",
      "ward": 25,
      "division": 20
    },
    {
      "Candidate": "Total",
      "Michael H O Brien": "59",
      "ward": 25,
      "division": 20
    }
  ],
  [
    {
      "Candidate": "",
      "Michael H O Brien": "Michael H O Brien",
      "ward": 25,
      "division": 21
    },
    {
      "Candidate": "Michael H O Brien",
      "Michael H O Brien": "70",
      "ward": 25,
      "division": 21
    },
    {
      "Candidate": "Total",
      "Michael H O Brien": "70",
      "ward": 25,
      "division": 21
    }
  ],
  [
    {
      "Candidate": "",
      "Michael H O Brien": "Michael H O Brien",
      "Write In": "Write In",
      "ward": 25,
      "division": 24
    },
    {
      "Candidate": "Michael H O Brien",
      "Michael H O Brien": "87",
      "Write In": "0",
      "ward": 25,
      "division": 24
    },
    {
      "Candidate": "Write In",
      "Michael H O Brien": "",
      "Write In": "1",
      "ward": 25,
      "division": 24
    },
    {
      "Candidate": "Total",
      "Michael H O Brien": "87",
      "Write In": "1",
      "ward": 25,
      "division": 24
    }
  ]
]
