[
  [
    {
      "Candidate": "",
      "Rhea Powell": "Rhea Powell",
      "Marylouise Isaacson": "Marylouise Isaacson",
      "Amanda Mcillmurray": "Amanda Mcillmurray",
      "Andi Perez": "Andi Perez",
      "Micah Mahjoubian": "Micah Mahjoubian",
      "Judi Golding Baker": "Judi Golding Baker",
      "Tom Young": "Tom Young",
      "Mariel J K Martin": "Mariel J K Martin",
      "Noam Kugelmass": "Noam Kugelmass",
      "Darrell L Clarke": "Darrell L Clarke",
      "Joe Celentano": "Joe Celentano",
      "Matthew D Myers": "Matthew D Myers",
      "Jon Geeting": "Jon Geeting",
      "Write In": "Write In",
      "ward": "All",
      "division": "All"
    },
    {
      "Candidate": "Rhea Powell",
      "Rhea Powell": "1608",
      "Marylouise Isaacson": "9855",
      "Amanda Mcillmurray": "9802",
      "Andi Perez": "8426",
      "Micah Mahjoubian": "8128",
      "Judi Golding Baker": "7991",
      "Tom Young": "7330",
      "Mariel J K Martin": "7600",
      "Noam Kugelmass": "7255",
      "Darrell L Clarke": "5205",
      "Joe Celentano": "6857",
      "Matthew D Myers": "3573",
      "Jon Geeting": "4461",
      "Write In": "16",
      "ward": "All",
      "division": "All"
    },
    {
      "Candidate": "Marylouise Isaacson",
      "Rhea Powell": "9855",
      "Marylouise Isaacson": "223",
      "Amanda Mcillmurray": "9322",
      "Andi Perez": "9030",
      "Micah Mahjoubian": "8553",
      "Judi Golding Baker": "8061",
      "Tom Young": "7352",
      "Mariel J K Martin": "8750",
      "Noam Kugelmass": "5825",
      "Darrell L Clarke": "6250",
      "Joe Celentano": "5042",
      "Matthew D Myers": "4976",
      "Jon Geeting": "3575",
      "Write In": "12",
      "ward": "All",
      "division": "All"
    },
    {
      "Candidate": "Amanda Mcillmurray",
      "Rhea Powell": "9802",
      "Marylouise Isaacson": "9322",
      "Amanda Mcillmurray": "471",
      "Andi Perez": "7427",
      "Micah Mahjoubian": "6391",
      "Judi Golding Baker": "7570",
      "Tom Young": "5728",
      "Mariel J K Martin": "7342",
      "Noam Kugelmass": "5640",
      "Darrell L Clarke": "4521",
      "Joe Celentano": "5046",
      "Matthew D Myers": "3419",
      "Jon Geeting": "3694",
      "Write In": "20",
      "ward": "All",
      "division": "All"
    },
    {
      "Candidate": "Andi Perez",
      "Rhea Powell": "8426",
      "Marylouise Isaacson": "9030",
      "Amanda Mcillmurray": "7427",
      "Andi Perez": "184",
      "Micah Mahjoubian": "7595",
      "Judi Golding Baker": "6404",
      "Tom Young": "6739",
      "Mariel J K Martin": "7625",
      "Noam Kugelmass": "5267",
      "Darrell L Clarke": "5741",
      "Joe Celentano": "4644",
      "Matthew D Myers": "4461",
      "Jon Geeting": "3736",
      "Write In": "10",
      "ward": "All",
      "division": "All"
    },
    {
      "Candidate": "Micah Mahjoubian",
      "Rhea Powell": "8128",
      "Marylouise Isaacson": "8553",
      "Amanda Mcillmurray": "6391",
      "Andi Perez": "7595",
      "Micah Mahjoubian": "448",
      "Judi Golding Baker": "5526",
      "Tom Young": "7162",
      "Mariel J K Martin": "6596",
      "Noam Kugelmass": "5704",
      "Darrell L Clarke": "5293",
      "Joe Celentano": "5099",
      "Matthew D Myers": "4022",
      "Jon Geeting": "2945",
      "Write In": "16",
      "ward": "All",
      "division": "All"
    },
    {
      "Candidate": "Judi Golding Baker",
      "Rhea Powell": "7991",
      "Marylouise Isaacson": "8061",
      "Amanda Mcillmurray": "7570",
      "Andi Perez": "6404",
      "Micah Mahjoubian": "5526",
      "Judi Golding Baker": "549",
      "Tom Young": "4525",
      "Mariel J K Martin": "6337",
      "Noam Kugelmass": "5061",
      "Darrell L Clarke": "4776",
      "Joe Celentano": "3433",
      "Matthew D Myers": "4473",
      "Jon Geeting": "2976",
      "Write In": "15",
      "ward": "All",
      "division": "All"
    },
    {
      "Candidate": "Tom Young",
      "Rhea Powell": "7330",
      "Marylouise Isaacson": "7352",
      "Amanda Mcillmurray": "5728",
      "Andi Perez": "6739",
      "Micah Mahjoubian": "7162",
      "Judi Golding Baker": "4525",
      "Tom Young": "570",
      "Mariel J K Martin": "5860",
      "Noam Kugelmass": "5545",
      "Darrell L Clarke": "4737",
      "Joe Celentano": "5510",
      "Matthew D Myers": "4220",
      "Jon Geeting": "3361",
      "Write In": "10",
      "ward": "All",
      "division": "All"
    },
    {
      "Candidate": "Mariel J K Martin",
      "Rhea Powell": "7600",
      "Marylouise Isaacson": "8750",
      "Amanda Mcillmurray": "7342",
      "Andi Perez": "7625",
      "Micah Mahjoubian": "6596",
      "Judi Golding Baker": "6337",
      "Tom Young": "5860",
      "Mariel J K Martin": "103",
      "Noam Kugelmass": "4365",
      "Darrell L Clarke": "5472",
      "Joe Celentano": "3764",
      "Matthew D Myers": "4524",
      "Jon Geeting": "2658",
      "Write In": "13",
      "ward": "All",
      "division": "All"
    },
    {
      "Candidate": "Noam Kugelmass",
      "Rhea Powell": "7255",
      "Marylouise Isaacson": "5825",
      "Amanda Mcillmurray": "5640",
      "Andi Perez": "5267",
      "Micah Mahjoubian": "5704",
      "Judi Golding Baker": "5061",
      "Tom Young": "5545",
      "Mariel J K Martin": "4365",
      "Noam Kugelmass": "293",
      "Darrell L Clarke": "3036",
      "Joe Celentano": "4586",
      "Matthew D Myers": "2928",
      "Jon Geeting": "3238",
      "Write In": "11",
      "ward": "All",
      "division": "All"
    },
    {
      "Candidate": "Darrell L Clarke",
      "Rhea Powell": "5205",
      "Marylouise Isaacson": "6250",
      "Amanda Mcillmurray": "4521",
      "Andi Perez": "5741",
      "Micah Mahjoubian": "5293",
      "Judi Golding Baker": "4776",
      "Tom Young": "4737",
      "Mariel J K Martin": "5472",
      "Noam Kugelmass": "3036",
      "Darrell L Clarke": "780",
      "Joe Celentano": "2590",
      "Matthew D Myers": "4492",
      "Jon Geeting": "2125",
      "Write In": "8",
      "ward": "All",
      "division": "All"
    },
    {
      "Candidate": "Joe Celentano",
      "Rhea Powell": "6857",
      "Marylouise Isaacson": "5042",
      "Amanda Mcillmurray": "5046",
      "Andi Perez": "4644",
      "Micah Mahjoubian": "5099",
      "Judi Golding Baker": "3433",
      "Tom Young": "5510",
      "Mariel J K Martin": "3764",
      "Noam Kugelmass": "4586",
      "Darrell L Clarke": "2590",
      "Joe Celentano": "644",
      "Matthew D Myers": "2196",
      "Jon Geeting": "3183",
      "Write In": "11",
      "ward": "All",
      "division": "All"
    },
    {
      "Candidate": "Matthew D Myers",
      "Rhea Powell": "3573",
      "Marylouise Isaacson": "4976",
      "Amanda Mcillmurray": "3419",
      "Andi Perez": "4461",
      "Micah Mahjoubian": "4022",
      "Judi Golding Baker": "4473",
      "Tom Young": "4220",
      "Mariel J K Martin": "4524",
      "Noam Kugelmass": "2928",
      "Darrell L Clarke": "4492",
      "Joe Celentano": "2196",
      "Matthew D Myers": "492",
      "Jon Geeting": "2053",
      "Write In": "7",
      "ward": "All",
      "division": "All"
    },
    {
      "Candidate": "Jon Geeting",
      "Rhea Powell": "4461",
      "Marylouise Isaacson": "3575",
      "Amanda Mcillmurray": "3694",
      "Andi Perez": "3736",
      "Micah Mahjoubian": "2945",
      "Judi Golding Baker": "2976",
      "Tom Young": "3361",
      "Mariel J K Martin": "2658",
      "Noam Kugelmass": "3238",
      "Darrell L Clarke": "2125",
      "Joe Celentano": "3183",
      "Matthew D Myers": "2053",
      "Jon Geeting": "351",
      "Write In": "8",
      "ward": "All",
      "division": "All"
    },
    {
      "Candidate": "Write In",
      "Rhea Powell": "16",
      "Marylouise Isaacson": "12",
      "Amanda Mcillmurray": "20",
      "Andi Perez": "10",
      "Micah Mahjoubian": "16",
      "Judi Golding Baker": "15",
      "Tom Young": "10",
      "Mariel J K Martin": "13",
      "Noam Kugelmass": "11",
      "Darrell L Clarke": "8",
      "Joe Celentano": "11",
      "Matthew D Myers": "7",
      "Jon Geeting": "8",
      "Write In": "19",
      "ward": "All",
      "division": "All"
    },
    {
      "Candidate": "Total",
      "Rhea Powell": "16573",
      "Marylouise Isaacson": "14538",
      "Amanda Mcillmurray": "13171",
      "Andi Perez": "12762",
      "Micah Mahjoubian": "12513",
      "Judi Golding Baker": "12008",
      "Tom Young": "11961",
      "Mariel J K Martin": "11599",
      "Noam Kugelmass": "10381",
      "Darrell L Clarke": "10118",
      "Joe Celentano": "9300",
      "Matthew D Myers": "8263",
      "Jon Geeting": "6726",
      "Write In": "55",
      "ward": "All",
      "division": "All"
    }
  ]
]
